[
  {
    "id": 1,
    "description": "vehicle_unlock_task-10000001",
    "task_type": "commander_level",
    "count": "50",
    "condition": "",
    "vehicle_id": 1,
    "group_type": 1,
    "function_control_id": 0
  },
  {
    "id": 2,
    "description": "vehicle_unlock_task-10000002",
    "task_type": "mission_medal_all",
    "count": "120",
    "condition": "",
    "vehicle_id": 1,
    "group_type": 1,
    "function_control_id": 0
  },
  {
    "id": 3,
    "description": "vehicle_unlock_task-10000003",
    "task_type": "i_gun_level",
    "count": "10",
    "condition": "100",
    "vehicle_id": 1,
    "group_type": 1,
    "function_control_id": 0
  },
  {
    "id": 4,
    "description": "vehicle_unlock_task-10000004",
    "task_type": "c_guide_complete",
    "count": "",
    "condition": "11487",
    "vehicle_id": 1,
    "group_type": 1,
    "function_control_id": 0
  },
  {
    "id": 5,
    "description": "vehicle_unlock_task-10000005",
    "task_type": "i_kill_enemy_all",
    "count": "1",
    "condition": "80",
    "vehicle_id": 2,
    "group_type": 1,
    "function_control_id": 0
  },
  {
    "id": 6,
    "description": "vehicle_unlock_task-10000006",
    "task_type": "mission_bestrank5",
    "count": "50",
    "condition": "",
    "vehicle_id": 2,
    "group_type": 1,
    "function_control_id": 0
  },
  {
    "id": 7,
    "description": "vehicle_unlock_task-10000007",
    "task_type": "i_squad_level",
    "count": "2",
    "condition": "100",
    "vehicle_id": 2,
    "group_type": 1,
    "function_control_id": 0
  },
  {
    "id": 8,
    "description": "vehicle_unlock_task-10000008",
    "task_type": "c_guide_complete",
    "count": "",
    "condition": "11486",
    "vehicle_id": 2,
    "group_type": 1,
    "function_control_id": 0
  }
]