{
  "chess_camp_type-10000001": "I.O.P.テクノロジー",
  "chess_camp_type-20000001": "第三次世界大戦期に立てられた工業製造会社。戦争期間中に90wishのペルシカから技術面での支援を受け、戦術人形の生産を始めた。",
  "chess_camp_type-10000002": "スヴァローグ重工",
  "chess_camp_type-20000002": "老舗の重工メーカー。軍需産業、エネルギー産業やインフラの整備等も行っており、スマートシティや新エネルギーの領域で多くの成果を出している。",
  "chess_camp_type-10000003": "16LABテクノロジー",
  "chess_camp_type-20000003": "IOPが資金を提供する新しい研究チーム。主要な研究対象は90wishが残した「ツェナープロトコル」。",
  "chess_camp_type-10000004": "鉄血工造",
  "chess_camp_type-20000004": "正式名称を鉄血工業製造会社（SANGVIS FERRI）といい、老舗の工業メーカーである。第三次世界大戦が終わると、AIを利用して新世代の戦術人形を開発した。"
}