{
  "sangvis_gasha-10000000": "Sangvis Ferri Joint Base",
  "sangvis_gasha-10000001": "Area S09 Sangvis Outpost",
  "sangvis_gasha-10001001": "Sector S09 S.F. Base Perimeter",
  "sangvis_gasha-10000002": "SP721 Command Center",
  "sangvis_gasha-10000003": "Segment SP914",
  "sangvis_gasha-10000004": "Segment SP5NANO",
  "sangvis_gasha-10000005": "Segment SPzh3000",
  "sangvis_gasha-10000006": "Segment SP24WR",
  "sangvis_gasha-10000007": "Subsector SP-7C",
  "sangvis_gasha-10000008": "Area S05 Anti-Air Command Post",
  "sangvis_gasha-10000009": "SP21 Auxiliary Processing Installation",
  "sangvis_gasha-10000010": "Area S02 Scales of Judgement",
  "sangvis_gasha-10000011": "Sangvis Ferri Manufacturing Terminal Core",
  "sangvis_gasha-10000012": "Area S09 Sangvis Outpost",
  "sangvis_gasha-10000013": "\"Hurricane\" N2 Secret Interrogation Room",
  "sangvis_gasha-10000014": "Sector S09 S.F. Base Perimeter",
  "sangvis_gasha-10000015": "SP721 Command Center",
  "sangvis_gasha-10000016": "\"Hurricane\" N7 Outer Defensive Line",
  "sangvis_gasha-10000017": "Segment SP914",
  "sangvis_gasha-10000018": "Segment SP5NANO",
  "sangvis_gasha-10000019": "SP Mobile Special Region",
  "sangvis_gasha-10000020": "Segment SPzh3000",
  "sangvis_gasha-10000021": "Segment SP24WR",
  "sangvis_gasha-10000022": "SPzh3000 Naval Warfare Platform",
  "sangvis_gasha-10000023": "Subsector SP-7C",
  "sangvis_gasha-10000024": "Area S05 Anti-Air Command Post",
  "sangvis_gasha-10000025": "SP21 Auxiliary Processing Installation",
  "sangvis_gasha-10000026": "Area S02 Scales of Judgement",
  "sangvis_gasha-10000027": "Area SP914 Nightmare Theater",
  "sangvis_gasha-10000028": "Sangvis Ferri Manufacturing Terminal Core",
  "sangvis_gasha-10000029": "\"Hurricane\" N2 Secret Interrogation Room",
  "sangvis_gasha-10000030": "Area SP5NANO Glacial Tundra",
  "sangvis_gasha-10000031": "\"Hurricane\" N7 Outer Defensive Line",
  "sangvis_gasha-10000032": "Area S09 Sangvis Outpost",
  "sangvis_gasha-10000033": "Sector SP721 Nightfall Corridor",
  "sangvis_gasha-10001002": "Sector S09 S.F. Base Perimeter"
}