{
  "adjutant_skin-10001001": "偽裝形態",
  "adjutant_skin-20001001": "通關「縱向應變-光之聲」解鎖",
  "adjutant_skin-10001003": "準備形態",
  "adjutant_skin-20001003": "獲取塔亞柔斯解鎖",
  "adjutant_skin-10001004": "戰鬥形態",
  "adjutant_skin-20001004": "獲取塔亞柔斯解鎖",
  "adjutant_skin-10001010": "常服",
  "adjutant_skin-20001010": "通關「慢休克-F20 日落」解鎖",
  "adjutant_skin-10001012": "戰鬥裝",
  "adjutant_skin-20001012": "獲取紗那解鎖",
  "adjutant_skin-10001015": "酣戰",
  "adjutant_skin-20001015": "獲取格雷解鎖",
  "adjutant_skin-10001016": "祈告",
  "adjutant_skin-20001016": "獲取格雷解鎖"
}