{
  "breakout_gun-9999999": "指揮官",
  "breakout_gun-19999999": "呀哈哈",
  "breakout_gun-10000001": "MDR",
  "breakout_gun-20000001": "戰鬥中會交替提高自身傷害及射速，每3秒替換一次",
  "breakout_gun-10000002": "G3",
  "breakout_gun-20000002": "發射榴彈對落點附近的敵人造成傷害，冷卻時間6秒",
  "breakout_gun-10000003": "ACR",
  "breakout_gun-20000003": "攻擊時使目標減速，持續2秒，冷卻時間6秒\n普通攻擊對被減速的目標造成的傷害提高",
  "breakout_gun-10000004": "wz.29",
  "breakout_gun-20000004": "提升自身射速，持續時間3秒，冷卻時間6秒",
  "breakout_gun-10000005": "M1加蘭德",
  "breakout_gun-20000005": "對射程內的隨機目標發動一次狙擊，冷卻時間3秒，可跨行攻擊",
  "breakout_gun-10000006": "四式",
  "breakout_gun-20000006": "攻擊時可以貫穿第1個目標，對射程內的第2個目標造成一半的傷害",
  "breakout_gun-10000007": "RPD",
  "breakout_gun-20000007": "自身攻擊提高，但會攻擊射程內的隨機目標，可跨行",
  "breakout_gun-10000008": "MG5",
  "breakout_gun-20000008": "每3次攻擊後下一次攻擊傷害提高",
  "breakout_gun-10000009": "MG338",
  "breakout_gun-20000009": "每次攻擊時提高自身傷害，換彈時清零",
  "breakout_gun-10000010": "AK-74U",
  "breakout_gun-20000010": "在場時使同一行的所有敵人傷害小幅下降，不可疊加",
  "breakout_gun-10000011": "蝎式",
  "breakout_gun-20000011": "投擲燃燒瓶對落點附近的敵人造成傷害並將其點燃，持續時間5秒，冷卻時間6秒",
  "breakout_gun-10000012": "P90",
  "breakout_gun-20000012": "戰鬥中持續提高自身閃避，達到最大層數後清零",
  "breakout_gun-10000013": "KSG",
  "breakout_gun-20000013": "提升自身護甲，持續時間3秒，冷卻時間6秒",
  "breakout_gun-10000014": "97式霰",
  "breakout_gun-20000014": "攻擊時擊退目標並將其減速，持續時間1秒",
  "breakout_gun-10000015": "MK3A1",
  "breakout_gun-20000015": "同時攻擊最近的3個目標，但射程降低",
  "breakout_gun-10000016": "柯爾特左輪",
  "breakout_gun-20000016": "在場時使同一行的所有友軍傷害小幅提升，不可疊加",
  "breakout_gun-10000017": "阿斯特拉左輪",
  "breakout_gun-20000017": "在場時使同一行的所有友軍射速小幅提升，不可疊加",
  "breakout_gun-10000018": "托卡列夫",
  "breakout_gun-20000018": "在場時使同一行的所有友軍迴避小幅提升，不可疊加"
}