{
  "mall-10000001": "",
  "mall-10000002": "",
  "mall-10000003": "",
  "mall-10000004": "",
  "mall-10000005": "",
  "mall-10000006": "",
  "mall-10000007": "",
  "mall-10000008": "",
  "mall-10000009": "",
  "mall-10000010": "",
  "mall-10000011": "",
  "mall-10000012": "",
  "mall-10000013": "",
  "mall-10000014": "",
  "mall-10000015": "",
  "mall-10000016": "",
  "mall-10000017": "",
  "mall-10000018": "",
  "mall-10000019": "",
  "mall-10000020": "",
  "mall-10000022": "",
  "mall-10000023": "",
  "mall-10000024": "",
  "mall-10000025": "",
  "mall-10000026": "",
  "mall-10000027": "",
  "mall-10000028": "",
  "mall-10000029": "",
  "mall-10000030": "特殊材料副本代幣",
  "mall-10000031": "",
  "mall-10000032": "",
  "mall-10000035": "",
  "mall-10000036": "",
  "mall-10000113": "盛夏特惠禮包",
  "mall-10000114": "盛夏資源禮包",
  "mall-10000115": "盛夏契約禮包",
  "mall-10000116": "裝備製造禮包",
  "mall-10000117": "一發入魂禮包",
  "mall-10000119": "中秋團圓禮包",
  "mall-10000120": "聖建資源禮包",
  "mall-10000121": "聖建契約禮包",
  "mall-10000122": "每日特惠禮包",
  "mall-10000123": "甜蜜誓約禮包",
  "mall-10000124": "一發入魂禮包",
  "mall-10000125": "每日作戰補給",
  "mall-10000126": "一發入魂禮包",
  "mall-10000127": "契約特惠禮包",
  "mall-10000128": "馬卡洛夫-南瓜熊熊",
  "mall-10000129": "M45-糖果快遞",
  "mall-10000130": "MK23-甜心小惡魔",
  "mall-10000131": "雙11特惠禮包",
  "mall-10000132": "甜蜜誓約禮包",
  "mall-10000133": "每日特惠禮包",
  "mall-10000134": "感恩回饋禮包",
  "mall-10000135": "聖建資源禮包",
  "mall-10000136": "聖建契約禮包",
  "mall-10000137": "冬日特惠禮包",
  "mall-10000138": "M14-聖誕巡遊禮服",
  "mall-10000139": "春田-聖善夜的祝福",
  "mall-10000140": "FAL-冬幕補給行動",
  "mall-10000141": "元旦禮包",
  "mall-10000142": "每日特惠禮包",
  "mall-10000143": "重建資源補給",
  "mall-10000144": "重建契約補給",
  "mall-10000145": "97式-牡丹魁",
  "mall-10000146": "一發入魂禮包",
  "mall-10000147": "每日特惠禮包",
  "mall-10000148": "甜蜜誓約禮包",
  "mall-10000149": "征戰補給禮包",
  "mall-10000150": "一發入魂禮包",
  "mall-10000154": "PK純白誓約禮包",
  "mall-10000152": "作戰補給禮包",
  "mall-10000153": "點券特惠禮包",
  "mall-10000151": "PK-與您同在",
  "mall-10000155": "復活節特惠禮包",
  "mall-10000156": "每日特惠禮包",
  "mall-10000157": "製造特惠禮包（MG）",
  "mall-10000158": "製造特惠禮包（AR）",
  "mall-10000162": "SR-3MP牧月之邀禮包",
  "mall-10000163": "莫辛納甘牧月之邀禮包",
  "mall-10000164": "蠍式牧月之邀禮包 ",
  "mall-10000159": "SR-3MP-黑兔瑪奇朵",
  "mall-10000160": "莫辛-納甘-月之海",
  "mall-10000161": "蝎式-深紅的星途",
  "mall-10000165": "作戰補給禮包",
  "mall-10000166": "裝備製造禮包",
  "mall-10000167": "每日特惠禮包",
  "mall-10000168": "一發入魂禮包",
  "mall-10000169": "95式-夏鳴蟬",
  "mall-10000170": "WA2000-魔鬼魚行動",
  "mall-10000172": "NTW-20-驕陽任務",
  "mall-10000171": "作戰補給禮包",
  "mall-10000173": "95式盛夏禮包",
  "mall-10000174": "WA2000盛夏禮包",
  "mall-10000175": "NTW-20盛夏禮包",
  "mall-10000201": "人力半價禮包",
  "mall-10000202": "彈藥半價禮包",
  "mall-10000203": "口糧半價禮包",
  "mall-10000204": "零件半價禮包",
  "mall-10000205": "裝備重造特惠",
  "mall-10000206": "訓練資料特惠",
  "mall-10000207": "每日特惠禮包",
  "mall-10000208": "一發入魂禮包",
  "mall-10000209": "七夕特惠禮包",
  "mall-10000210": "每日特惠禮包",
  "mall-10000211": "作戰補給禮包",
  "mall-10000212": "契約特惠禮包",
  "mall-10000213": "人力半價禮包",
  "mall-10000214": "彈藥半價禮包",
  "mall-10000215": "口糧半價禮包",
  "mall-10000216": "零件半價禮包",
  "mall-10000217": "人形重造特惠",
  "mall-10000218": "每日特惠禮包",
  "mall-10000219": "人力半價禮包",
  "mall-10000220": "彈藥半價禮包",
  "mall-10000221": "口糧半價禮包",
  "mall-10000222": "零件半價禮包",
  "mall-10000223": "月夕超值禮盒",
  "mall-10000224": "IWS 2000-第七封印者",
  "mall-10000225": "每日特惠禮包",
  "mall-10000226": "雙11狂歡禮包",
  "mall-10000227": "甜蜜誓約禮包",
  "mall-10000228": "戰術人形：德麗莎",
  "mall-10000229": "戰術人形：希兒",
  "mall-10000230": "戰術妖精：耀夜姬",
  "mall-10000231": "戰術妖精：柯蘿伊",
  "mall-10000232": "裝扮：希兒的祭禮",
  "mall-10000233": "頭像：獨法師-琪亞娜",
  "mall-10000234": "頭像：獨法師-芽衣",
  "mall-10000235": "頭像：獨法師-布洛妮婭",
  "mall-10000236": "頭像：獨法師-德麗莎",
  "mall-10000237": "頭像：獨法師-姬子",
  "mall-10000238": "頭像：獨法師-希兒",
  "mall-10000239": "名片背景：獨法師-封面",
  "mall-10000240": "名片背景：獨法師-崩壞降臨",
  "mall-10000241": "禮物：無法回頭的命運",
  "mall-10000242": "禮物：光明的詩歌",
  "mall-10000243": "琪亞娜的禮裝",
  "mall-10000244": "布洛妮婭的裝甲",
  "mall-10000245": "競爭者-歌劇魅影",
  "mall-10000246": "AEK-999-極道車神",
  "mall-10000247": "每日特惠禮包",
  "mall-10000248": "人力半價禮包",
  "mall-10000249": "彈藥半價禮包",
  "mall-10000250": "口糧半價禮包",
  "mall-10000251": "零件半價禮包",
  "mall-10000252": "契約半價禮包",
  "mall-10000253": "裝扮：格林娜-冬幕派對",
  "mall-10000254": "傢俱：聖誕特供豆袋沙發",
  "mall-10000255": "寵物：聖誕巴哥犬",
  "mall-10000256": "裝備：專用戰術記憶體",
  "mall-10000257": "裝備：16Lab空尖彈",
  "mall-10000258": "裝備：16lab熱光學披風",
  "mall-10000259": "基地背景：平安夜一角",
  "mall-10000260": "名片背景：與大自然的聖誕之約",
  "mall-10000261": "頭像：戰術白貂",
  "mall-10000262": "頭像：格里芬聖誕繡章",
  "mall-10000263": "頭像：鐵血聖誕繡章",
  "mall-10000264": "頭像：迷之聖誕老人",
  "mall-10000265": "克魯格的採購幣",
  "mall-10000266": "赫麗安的採購幣",
  "mall-10000267": "格琳娜的採購幣",
  "mall-10000268": "帕斯卡的採購幣",
  "mall-10000269": "禮物：蛋奶草莓芝士",
  "mall-10000270": "禮物：作戰報告書",
  "mall-10000271": "Zas M21-獻上槍聲的雪姑娘",
  "mall-10000272": "每日特惠禮包",
  "mall-10000273": "作戰補給禮包",
  "mall-10000274": "KLIN-三羽烏",
  "mall-10000275": "一發入魂禮包",
  "mall-10000276": "除舊布新禮包",
  "mall-10000277": "每日特惠禮包",
  "mall-10000278": "契約超值禮盒",
  "mall-10000279": "人力半價禮包",
  "mall-10000280": "彈藥半價禮包",
  "mall-10000281": "口糧半價禮包",
  "mall-10000282": "零件半價禮包",
  "mall-10000283": "Mk23-蜂糖花",
  "mall-10000284": "S.A.T.8-梅花印",
  "mall-10000285": "ART556-蓮花白",
  "mall-10000286": "甜蜜誓約禮包",
  "mall-10000287": "每日特惠禮包",
  "mall-10000288": "元宵節特惠",
  "mall-10000289": "G36-純白矢車菊",
  "mall-10000290": "契約半價禮包",
  "mall-10000291": "人力半價禮包",
  "mall-10000292": "彈藥半價禮包",
  "mall-10000293": "口糧半價禮包",
  "mall-10000294": "零件半價禮包",
  "mall-10000295": "傢俱：復活節的白兔",
  "mall-10000296": "傢俱：兔子麥克風",
  "mall-10000297": "傢俱：兔耳朵音箱",
  "mall-10000298": "傢俱：彩蛋掛飾：小心引爆",
  "mall-10000299": "裝備：藍色加厚披風",
  "mall-10000300": "裝備：16Lab6-24X56",
  "mall-10000301": "裝備：16Lab高速彈",
  "mall-10000302": "名片背景：復活節警告",
  "mall-10000303": "頭像：復活節白兔",
  "mall-10000304": "採購幣",
  "mall-10000305": "記憶碎片*2",
  "mall-10000306": "復活節特惠",
  "mall-10000307": "每日特惠禮包",
  "mall-10000308": "一發入魂禮包",
  "mall-10000309": "心智升級特惠",
  "mall-10000310": "人形：菲爾",
  "mall-10000311": "菲爾專屬裝備：漆黑之貓",
  "mall-10000312": "妖精：普蕾婭&卡米莉婭",
  "mall-10000313": "妖精：希依",
  "mall-10000314": "傢俱：舊日的音遊街機",
  "mall-10000315": "傢俱：夢中的水晶球",
  "mall-10000316": "名片背景：口袋城大冒險",
  "mall-10000317": "頭像：黑騎士",
  "mall-10000318": "頭像：風語者",
  "mall-10000319": "頭像：墮天使",
  "mall-10000320": "頭像：白人偶",
  "mall-10000321": "頭像：貓戰士",
  "mall-10000322": "頭像：克莉爾",
  "mall-10000323": "頭像：菲爾",
  "mall-10000324": "頭像：口袋城女王",
  "mall-10000325": "作戰報告書",
  "mall-10000326": "每日特惠禮包",
  "mall-10000327": "勞動節特惠",
  "mall-10000328": "克莉爾口袋城裝扮禮包",
  "mall-10000329": "菲爾口袋城裝扮禮包",
  "mall-10000330": "裝扮：格琳娜-黑貓小姐",
  "mall-10000331": "Daily Special Offer Package",
  "mall-10000332": "契約半價禮包",
  "mall-10000333": "人力半價禮包",
  "mall-10000334": "彈藥半價禮包",
  "mall-10000335": "口糧半價禮包",
  "mall-10000336": "零件半價禮包",
  "mall-10000337": "維爾德MKⅡ-夜幕危機",
  "mall-10000338": "柯爾特左輪-奇跡女王",
  "mall-10000339": "ZasM21-白棋王后",
  "mall-10000340": "戰術人形：湯姆森",
  "mall-10000341": "戰術人形：Vector",
  "mall-10000342": "戰術人形：Kar98k",
  "mall-10000343": "戰術人形：WA2000",
  "mall-10000344": "戰術人形：李-恩菲爾德",
  "mall-10000345": "戰術人形：NTW-20",
  "mall-10000346": "戰術人形：G41",
  "mall-10000347": "戰術人形：HK416",
  "mall-10000348": "戰術人形：灰熊MkⅤ",
  "mall-10000349": "戰術人形：M950A",
  "mall-10000350": "戰術人形：G36C",
  "mall-10000351": "戰術人形：FAL",
  "mall-10000352": "戰術人形：MG5",
  "mall-10000353": "戰術人形：內蓋夫",
  "mall-10000354": "戰術人形：維爾德MkⅡ",
  "mall-10000355": "戰術人形：索米",
  "mall-10000356": "戰術人形：G11",
  "mall-10000357": "戰術人形：MG4",
  "mall-10000358": "戰術人形：NZ75",
  "mall-10000359": "戰術人形：79式",
  "mall-10000360": "戰術人形：M99",
  "mall-10000361": "戰術人形：95式",
  "mall-10000362": "戰術人形：97式",
  "mall-10000363": "戰術人形：SR-3MP",
  "mall-10000364": "戰術人形：IWS 2000",
  "mall-10000365": "戰術人形：KSG",
  "mall-10000366": "戰術人形：Saiga-12",
  "mall-10000367": "戰術人形：RFB",
  "mall-10000368": "戰術人形：PKP",
  "mall-10000369": "戰術人形：T91",
  "mall-10000370": "戰術人形：競爭者",
  "mall-10000371": "戰術人形：S.A.T.8",
  "mall-10000372": "戰術人形：K2",
  "mall-10000373": "戰術人形：Zas M21",
  "mall-10000374": "戰術人形：卡爾卡諾M1891",
  "mall-10000375": "戰術人形：卡爾卡諾M91/38",
  "mall-10000376": "戰術人形：AN-94",
  "mall-10000377": "戰術人形：AK-12",
  "mall-10000378": "頭像：真核面具紀念頭像",
  "mall-10000379": "每日特惠禮包",
  "mall-10000380": "盛夏特惠禮包",
  "mall-10000381": "卡爾卡諾M1891-勇敢的小卡諾",
  "mall-10000382": "戰術人形：TAC-50",
  "mall-10000383": "寵物：端午粽子貓",
  "mall-10000384": "宿舍家裝：端午粽子鞦韆",
  "mall-10000385": "宿舍家裝：端午節龍舟",
  "mall-10000386": "宿舍家裝：端午傳統鼓樂",
  "mall-10000387": "裝備：16LabMARS",
  "mall-10000388": "裝備：16LabT4外骨骼",
  "mall-10000389": "名片：粽武節",
  "mall-10000390": "頭像：合金粽備",
  "mall-10000391": "頭像：粽子貓",
  "mall-10000392": "採購幣",
  "mall-10000393": "作戰報告書",
  "mall-10000394": "契約半價禮包",
  "mall-10000395": "人力半價禮包",
  "mall-10000396": "彈藥半價禮包",
  "mall-10000397": "口糧半價禮包",
  "mall-10000398": "零件半價禮包",
  "mall-10000399": "每日特惠禮包",
  "mall-10000400": "夏日特惠禮包",
  "mall-10000401": "心智升級特惠",
  "mall-10000402": "每日特惠禮包",
  "mall-10000403": "8月特惠禮包",
  "mall-10000414": "七夕特惠禮包",
  "mall-10000404": "人形：Five-seveN",
  "mall-10000405": "裝扮：格琳娜-鑽石與煙花",
  "mall-10000406": "花火大會主題背景",
  "mall-10000407": "花火大會寵物",
  "mall-10000408": "花火大會鼓",
  "mall-10000409": "花火大會轎子",
  "mall-10000410": "花火大會頭像",
  "mall-10000411": "增幅膠囊",
  "mall-10000412": "作戰報告書",
  "mall-10000413": "採購幣",
  "mall-10000415": "FAL-FAL的夏天",
  "mall-10000416": "MP7-糖果槍彈",
  "mall-10000417": "AN-94-潛水鐘與人偶",
  "mall-10000418": "G36-和G36的五十天",
  "mall-10000419": "每日特惠禮包",
  "mall-10000420": "9月特惠禮包",
  "mall-10000421": "契約半價禮包",
  "mall-10000422": "人力半價禮包",
  "mall-10000423": "彈藥半價禮包",
  "mall-10000424": "口糧半價禮包",
  "mall-10000425": "零件半價禮包",
  "mall-10000426": "每日特惠禮包",
  "mall-10000427": "10月特惠禮包",
  "mall-10000428": "契約半價禮包",
  "mall-10000429": "人力半價禮包",
  "mall-10000430": "彈藥半價禮包",
  "mall-10000431": "口糧半價禮包",
  "mall-10000432": "零件半價禮包",
  "mall-10000433": "每日特惠禮包",
  "mall-10000434": "11月特惠禮包",
  "mall-10000435": "巧克力餅乾禮包",
  "mall-10000436": "冬至獻禮超超值禮包",
  "mall-10000437": "心智升級特惠",
  "mall-10000438": "PM-06-翱翔天空之法",
  "mall-10000439": "每日特惠禮包",
  "mall-10000440": "12月特惠禮包",
  "mall-10000441": "人力半價禮包",
  "mall-10000442": "彈藥半價禮包",
  "mall-10000443": "口糧半價禮包",
  "mall-10000444": "零件半價禮包",
  "mall-10000445": "契約半價禮包",
  "mall-10000446": "P90-緋紅渦輪",
  "mall-10000447": "G36-每個孩子的聖誕夢",
  "mall-10000448": "背景：冬幕將至",
  "mall-10000449": "寵物：馴貓",
  "mall-10000450": "傢俱：甜蜜的熊",
  "mall-10000451": "傢俱：聖誕貓窩",
  "mall-10000452": "名片：戰術馴鹿",
  "mall-10000453": "頭像：糖果魔杖",
  "mall-10000454": "頭像：戰術馴鹿",
  "mall-10000455": "採購幣",
  "mall-10000456": "作戰報告書",
  "mall-10000457": "特種作戰報告書",
  "mall-10000458": "禮物：蛋奶草莓芝士",
  "mall-10000459": "元旦特惠禮包",
  "mall-10000460": "元旦尊享禮包",
  "mall-10000461": "每日特惠禮包",
  "mall-10000462": "卡爾卡諾M1891-起始的鐘聲",
  "mall-10000463": "一〇〇式-槍使巫女",
  "mall-10000464": "M1014-雪月花",
  "mall-10000465": "戰術人形：湯姆森",
  "mall-10000466": "戰術人形：Vector",
  "mall-10000467": "戰術人形：MP7",
  "mall-10000468": "戰術人形：Kar98k",
  "mall-10000469": "戰術人形：WA2000",
  "mall-10000470": "戰術人形：李-恩菲爾德",
  "mall-10000471": "戰術人形：NTW-20",
  "mall-10000472": "戰術人形：G41",
  "mall-10000473": "戰術人形：HK416",
  "mall-10000474": "戰術人形：灰熊MkⅤ",
  "mall-10000475": "戰術人形：M950A",
  "mall-10000476": "戰術人形：G36C",
  "mall-10000477": "戰術人形：FAL",
  "mall-10000478": "戰術人形：MG5",
  "mall-10000479": "戰術人形：內蓋夫",
  "mall-10000480": "戰術人形：維爾德MkⅡ",
  "mall-10000481": "戰術人形：索米",
  "mall-10000482": "戰術人形：G11",
  "mall-10000483": "戰術人形：MG4",
  "mall-10000484": "戰術人形：NZ75",
  "mall-10000485": "戰術人形：79式",
  "mall-10000486": "戰術人形：M99",
  "mall-10000487": "戰術人形：95式",
  "mall-10000488": "戰術人形：97式",
  "mall-10000489": "戰術人形：SR-3MP",
  "mall-10000490": "戰術人形：IWS 2000",
  "mall-10000491": "戰術人形：KSG",
  "mall-10000492": "戰術人形：Saiga-12",
  "mall-10000493": "戰術人形：AA-12",
  "mall-10000494": "戰術人形：FP-6",
  "mall-10000495": "戰術人形：RFB",
  "mall-10000496": "戰術人形：PKP",
  "mall-10000497": "戰術人形：T91",
  "mall-10000498": "戰術人形：競爭者",
  "mall-10000499": "戰術人形：S.A.T.8",
  "mall-10000500": "戰術人形：K2",
  "mall-10000501": "戰術人形：Zas M21",
  "mall-10000502": "戰術人形：卡爾卡諾M1891",
  "mall-10000503": "戰術人形：卡爾卡諾M91/38",
  "mall-10000504": "戰術人形：AN-94",
  "mall-10000505": "戰術人形：AK-12",
  "mall-10000506": "戰術人形：C-MS",
  "mall-10000507": "戰術人形：MDR",
  "mall-10000508": "戰術人形：一〇〇式",
  "mall-10000509": "戰術人形：Px4 風暴",
  "mall-10000510": "戰術人形：K11",
  "mall-10000511": "戰術人形：88式",
  "mall-10000512": "戰術人形：64式自",
  "mall-10000513": "戰術人形：P90",
  "mall-10000514": "真核面具紀念頭像·異構體",
  "mall-10000515": "迎春特惠禮包",
  "mall-10000516": "每日特惠禮包",
  "mall-10000517": "甜蜜誓約禮包",
  "mall-10000518": "IWS 2000-薄雪絨",
  "mall-10000519": "人力半價禮包",
  "mall-10000520": "彈藥半價禮包",
  "mall-10000521": "口糧半價禮包",
  "mall-10000522": "零件半價禮包",
  "mall-10000523": "契約半價禮包",
  "mall-10000524": "每日特惠禮包",
  "mall-10000525": "3月特惠禮包",
  "mall-10000526": "裝扮：格琳娜-戀人絮語",
  "mall-10000527": "傢俱：藍莓夜紅酒桌",
  "mall-10000528": "傢俱：十日談麋鹿像",
  "mall-10000529": "寵物：情書加急特種鴿",
  "mall-10000530": "16Lab光學瞄具",
  "mall-10000531": "名片：誓約聖所",
  "mall-10000532": "頭像：加急特種鴿",
  "mall-10000533": "頭像：酒心巧克狗",
  "mall-10000534": "採購幣",
  "mall-10000535": "作戰報告書",
  "mall-10000536": "強化膠囊",
  "mall-10000537": "重裝補給禮包",
  "mall-10000538": "G36C-邁出步伐的你",
  "mall-10000539": "每日特惠禮包",
  "mall-10000540": "4月特惠禮包",
  "mall-10000541": "人力半價禮包",
  "mall-10000542": "彈藥半價禮包",
  "mall-10000543": "口糧半價禮包",
  "mall-10000544": "零件半價禮包",
  "mall-10000545": "契約半價禮包",
  "mall-10000546": "5月特惠禮包",
  "mall-10000547": "每日特惠禮包",
  "mall-10000548": "內蓋夫-黑石姬",
  "mall-10000549": "戰術人形：KSG",
  "mall-10000550": "戰術人形：Saiga-12",
  "mall-10000551": "戰術人形：AA-12",
  "mall-10000552": "戰術人形：FP-6",
  "mall-10000553": "戰術人形：S.A.T.8",
  "mall-10000554": "戰術人形：MG5",
  "mall-10000555": "戰術人形：內蓋夫",
  "mall-10000556": "戰術人形：MG4",
  "mall-10000557": "戰術人形：PKP",
  "mall-10000558": "戰術人形：88式",
  "mall-10000559": "戰術人形：MG36",
  "mall-10000560": "戰術人形：G41",
  "mall-10000561": "戰術人形：HK416",
  "mall-10000562": "戰術人形：FAL",
  "mall-10000563": "戰術人形：G11",
  "mall-10000564": "戰術人形：95式",
  "mall-10000565": "戰術人形：97式",
  "mall-10000566": "戰術人形：RFB",
  "mall-10000567": "戰術人形：T91",
  "mall-10000568": "戰術人形：K2",
  "mall-10000569": "戰術人形：Zas M21",
  "mall-10000570": "戰術人形：AK-12",
  "mall-10000571": "戰術人形：AN-94",
  "mall-10000572": "戰術人形：MDR",
  "mall-10000573": "戰術人形：K11",
  "mall-10000574": "戰術人形：64式自",
  "mall-10000575": "戰術人形：Kar98k",
  "mall-10000576": "戰術人形：WA2000",
  "mall-10000577": "戰術人形：李-恩菲爾德",
  "mall-10000578": "戰術人形：NTW-20",
  "mall-10000579": "戰術人形：M99",
  "mall-10000580": "戰術人形：IWS 2000",
  "mall-10000581": "戰術人形：卡爾卡諾M1891",
  "mall-10000582": "戰術人形：卡爾卡諾M91/38",
  "mall-10000583": "戰術人形：M200",
  "mall-10000584": "戰術人形：QBU-88",
  "mall-10000585": "戰術人形：湯姆森",
  "mall-10000586": "戰術人形：Vector",
  "mall-10000587": "戰術人形：G36C",
  "mall-10000588": "戰術人形：索米",
  "mall-10000589": "戰術人形：79式",
  "mall-10000590": "戰術人形：SR-3MP",
  "mall-10000591": "戰術人形：C-MS",
  "mall-10000592": "戰術人形：一〇〇式",
  "mall-10000593": "戰術人形：P90",
  "mall-10000594": "戰術人形：MP7",
  "mall-10000595": "戰術人形：灰熊MkⅤ",
  "mall-10000596": "戰術人形：M950A",
  "mall-10000597": "戰術人形：維爾德MkⅡ",
  "mall-10000598": "戰術人形：NZ75",
  "mall-10000599": "戰術人形：競爭者",
  "mall-10000600": "戰術人形：Px4 風暴",
  "mall-10000601": "戰術人形：PA-15",
  "mall-10000602": "頭像：真核面具紀念頭像·三週年",
  "mall-10000603": "人力半價禮包",
  "mall-10000604": "彈藥半價禮包",
  "mall-10000605": "口糧半價禮包",
  "mall-10000606": "零件半價禮包",
  "mall-10000607": "契約半價禮包",
  "mall-10000608": "重裝補給禮包",
  "mall-10000609": "心智升級特惠",
  "mall-10000610": "G28-月光與祖母綠",
  "mall-10000611": "雷電-黑天鵝的夢",
  "mall-10000612": "AK-12-靜寂蒼藍",
  "mall-10000613": "79式-星夜狐步",
  "mall-10000614": "6月特惠禮包",
  "mall-10000615": "每日特惠禮包",
  "mall-10000616": "桃樂絲聖誕裝扮禮包",
  "mall-10000617": "戰術人形：桃樂絲·海茲",
  "mall-10000618": "戰術人形：阿爾瑪·阿瑪斯",
  "mall-10000619": "戴娜專屬裝備：加強型機械臂",
  "mall-10000620": "桃樂絲專屬裝備：MIRD5級彈藥",
  "mall-10000621": "賽伊專屬裝備：白騎士制式裝甲",
  "mall-10000622": "史黛拉專屬裝備：電子義眼",
  "mall-10000623": "阿爾瑪專屬裝備：機械義手",
  "mall-10000624": "妖精：安娜·格雷姆",
  "mall-10000625": "名片：歡迎來到VA-11酒吧",
  "mall-10000626": "頭像：啤酒浪潮",
  "mall-10000627": "頭像：紅色鐵拳大滿貫",
  "mall-10000628": "頭像：貓咪朋友不會離開",
  "mall-10000629": "頭像：敬這該死的世界",
  "mall-10000630": "頭像：親愛的貝基",
  "mall-10000631": "頭像：超級小不點隊長",
  "mall-10000632": "寵物：跩柴犬",
  "mall-10000633": "打折啤酒",
  "mall-10000634": "Mulan Tea",
  "mall-10000635": "特種作戰報告書",
  "mall-10000636": "7月特惠禮包",
  "mall-10000637": "每日特惠禮包",
  "mall-10000638": "K11-小小科學家",
  "mall-10000639": "裝扮：謝爾久科夫-黑鴉救生員",
  "mall-10000640": "傢俱：海灘巡邏車",
  "mall-10000641": "傢俱：海灘救生椅",
  "mall-10000642": "寵物：搜救巴哥犬",
  "mall-10000643": "16Lab空尖彈",
  "mall-10000644": "名片：硬核西瓜節",
  "mall-10000645": "頭像：夏日守護者",
  "mall-10000646": "採購幣",
  "mall-10000647": "校准點券",
  "mall-10000648": "替代核心",
  "mall-10000649": "作戰報告書",
  "mall-10000650": "人力半價禮包",
  "mall-10000651": "彈藥半價禮包",
  "mall-10000652": "口糧半價禮包",
  "mall-10000653": "零件半價禮包",
  "mall-10000654": "契約半價禮包",
  "mall-10000655": "每日特惠禮包",
  "mall-10000656": "8月特惠禮包",
  "mall-10000657": "路易士-防曬大作戰",
  "mall-10000658": "七夕特惠禮包",
  "mall-10001211": "夏日休閒男性頭部",
  "mall-10001212": "夏日休閒女性頭部",
  "mall-10001220": "輕便海灘眼鏡",
  "mall-10001231": "健身成果（男）",
  "mall-10001232": "雙綁帶比基尼（女）",
  "mall-10001240": "夏日情懷配件",
  "mall-10001251": "平角沙灘短褲（男）",
  "mall-10001252": "沙灘休閒鞋（女）",
  "mall-10000667": "戰術人形：KSG",
  "mall-10000668": "戰術人形：Saiga-12",
  "mall-10000669": "戰術人形：AA-12",
  "mall-10000670": "戰術人形：FP-6",
  "mall-10000671": "戰術人形：S.A.T.8",
  "mall-10000672": "戰術人形：MG5",
  "mall-10000673": "戰術人形：內蓋夫",
  "mall-10000674": "戰術人形：MG4",
  "mall-10000675": "戰術人形：PKP",
  "mall-10000676": "戰術人形：88式",
  "mall-10000677": "戰術人形：MG36",
  "mall-10000678": "戰術人形：G41",
  "mall-10000679": "戰術人形：HK416",
  "mall-10000680": "戰術人形：FAL",
  "mall-10000681": "戰術人形：G11",
  "mall-10000682": "戰術人形：95式",
  "mall-10000683": "戰術人形：97式",
  "mall-10000684": "戰術人形：RFB",
  "mall-10000685": "戰術人形：T91",
  "mall-10000686": "戰術人形：K2",
  "mall-10000687": "戰術人形：Zas M21",
  "mall-10000688": "戰術人形：AK-12",
  "mall-10000689": "戰術人形：AN-94",
  "mall-10000690": "戰術人形：MDR",
  "mall-10000691": "戰術人形：K11",
  "mall-10000692": "戰術人形：64式自",
  "mall-10000693": "戰術人形：ADS",
  "mall-10000694": "戰術人形：Kar98k",
  "mall-10000695": "戰術人形：WA2000",
  "mall-10000696": "戰術人形：李-恩菲爾德",
  "mall-10000697": "戰術人形：NTW-20",
  "mall-10000698": "戰術人形：M99",
  "mall-10000699": "戰術人形：IWS 2000",
  "mall-10000700": "戰術人形：卡爾卡諾M1891",
  "mall-10000701": "戰術人形：卡爾卡諾M91/38",
  "mall-10000702": "戰術人形：M200",
  "mall-10000703": "戰術人形：QBU-88",
  "mall-10000704": "戰術人形：湯姆森",
  "mall-10000705": "戰術人形：Vector",
  "mall-10000706": "戰術人形：G36C",
  "mall-10000707": "戰術人形：索米",
  "mall-10000708": "戰術人形：79式",
  "mall-10000709": "戰術人形：SR-3MP",
  "mall-10000710": "戰術人形：C-MS",
  "mall-10000711": "戰術人形：一〇〇式",
  "mall-10000712": "戰術人形：P90",
  "mall-10000713": "戰術人形：MP7",
  "mall-10000714": "戰術人形：灰熊MkⅤ",
  "mall-10000715": "戰術人形：M950A",
  "mall-10000716": "戰術人形：維爾德MkⅡ",
  "mall-10000717": "戰術人形：NZ75",
  "mall-10000718": "戰術人形：競爭者",
  "mall-10000719": "戰術人形：Px4 風暴",
  "mall-10000720": "戰術人形：PA-15",
  "mall-10000721": "頭像：真核面具紀念頭像·裂變鏈結",
  "mall-10000722": "心智升級特惠",
  "mall-10000723": "每日特惠禮包",
  "mall-10000724": "9月特惠禮包",
  "mall-10001411": "夏夜清爽背頭",
  "mall-10001412": "流影簪花編髮",
  "mall-10001420": "夏夜祭典頭飾",
  "mall-10001431": "夏夜浴衣上裝",
  "mall-10001432": "流影浴衣上裝",
  "mall-10001440": "流影和式紙燈",
  "mall-10001451": "夏夜輕便木屐",
  "mall-10001452": "流影夢境裙裾",
  "mall-10000725": "人力半價禮包",
  "mall-10000726": "彈藥半價禮包",
  "mall-10000727": "口糧半價禮包",
  "mall-10000728": "零件半價禮包",
  "mall-10000729": "契約半價禮包",
  "mall-10000730": "95式-純白畢業祭",
  "mall-10000731": "Mk23-宣告開學的貓之歌",
  "mall-10000732": "TMP-喵稜鏡威力",
  "mall-10000733": "每日特惠禮包",
  "mall-10000734": "10月特惠禮包",
  "mall-10000735": "人力半價禮包",
  "mall-10000736": "彈藥半價禮包",
  "mall-10000737": "口糧半價禮包",
  "mall-10000738": "零件半價禮包",
  "mall-10000739": "契約半價禮包",
  "mall-10000740": "重裝補給禮包",
  "mall-10001611": "塗髮膠的阿尼基飛機頭",
  "mall-10001612": "吹好造型的大姐頭披髮",
  "mall-10001620": "出街必備道具",
  "mall-10001631": "阿尼基的必勝棒球衫",
  "mall-10001632": "大姐頭的無敵中間服",
  "mall-10001640": "不良的臻品玩具",
  "mall-10001651": "贏過團戰的牛仔褲",
  "mall-10001652": "橫掃學院街的飛腿",
  "mall-10000741": "裝扮：KSVK-月暗面漫步",
  "mall-10000742": "傢俱：甜美治療椅",
  "mall-10000743": "名片：狂潮落幕時",
  "mall-10000744": "頭像：傳頌使者",
  "mall-10000745": "頭像：詭夜對決",
  "mall-10000746": "16Lab空尖彈",
  "mall-10000747": "16Lab高速彈",
  "mall-10000748": "採購幣",
  "mall-10000749": "作戰報告書",
  "mall-10000750": "特種作戰報告書",
  "mall-10000751": "蛋奶草莓芝士",
  "mall-10000752": "每日特惠禮包",
  "mall-10000753": "11月特惠禮包",
  "mall-10000754": "97式霰-奇謀妙策九七計",
  "mall-10001720": "萬聖詭月·傳說頭飾",
  "mall-10000755": "巧克力餅乾特供禮包",
  "mall-10000756": "巧克力餅乾尊享禮包",
  "mall-10000757": "人力半價禮包",
  "mall-10000758": "彈藥半價禮包",
  "mall-10000759": "口糧半價禮包",
  "mall-10000760": "零件半價禮包",
  "mall-10000761": "契約半價禮包",
  "mall-10000762": "每日特惠禮包",
  "mall-10000763": "12月特惠禮包",
  "mall-10000764": "心智升級特惠",
  "mall-10000765": "裝扮：蜜獾-聖誕公主和不笑貝特",
  "mall-10000766": "傢俱：聖誕馴蟻",
  "mall-10000767": "名片：穿越時空的擁抱",
  "mall-10000768": "頭像：要抱抱！",
  "mall-10000769": "頭像：聖誕快樂汪！",
  "mall-10000770": "裝備：RFB前導軌",
  "mall-10000771": "裝備：折疊槍托",
  "mall-10000772": "採購幣",
  "mall-10000773": "作戰報告書",
  "mall-10000774": "特種作戰報告書",
  "mall-10000775": "蛋奶草莓芝士",
  "mall-10000776": "HK21-銀狐的⅑月台",
  "mall-10001811": "精緻卷髮",
  "mall-10001812": "活力馬尾",
  "mall-10001820": "派對頭飾",
  "mall-10001831": "禦寒大衣",
  "mall-10001832": "保暖外套",
  "mall-10001840": "待送驚喜",
  "mall-10001851": "耐磨長褲",
  "mall-10001852": "冬季熱褲",
  "mall-10000777": "人力半價禮包",
  "mall-10000778": "彈藥半價禮包",
  "mall-10000779": "口糧半價禮包",
  "mall-10000780": "零件半價禮包",
  "mall-10000781": "契約半價禮包",
  "mall-10000782": "每日特惠禮包",
  "mall-10000783": "元旦特惠禮包",
  "mall-10000784": "元旦尊享禮包",
  "mall-10000785": "戰術人形：KSG",
  "mall-10000786": "戰術人形：Saiga-12",
  "mall-10000787": "戰術人形：AA-12",
  "mall-10000788": "戰術人形：FP-6",
  "mall-10000789": "戰術人形：S.A.T.8",
  "mall-10000790": "戰術人形：MG5",
  "mall-10000791": "戰術人形：內蓋夫",
  "mall-10000792": "戰術人形：MG4",
  "mall-10000793": "戰術人形：PKP",
  "mall-10000794": "戰術人形：88式",
  "mall-10000795": "戰術人形：MG36",
  "mall-10000796": "戰術人形：G41",
  "mall-10000797": "戰術人形：HK416",
  "mall-10000798": "戰術人形：FAL",
  "mall-10000799": "戰術人形：G11",
  "mall-10000800": "戰術人形：95式",
  "mall-10000801": "戰術人形：97式",
  "mall-10000802": "戰術人形：RFB",
  "mall-10000803": "戰術人形：T91",
  "mall-10000804": "戰術人形：K2",
  "mall-10000805": "戰術人形：Zas M21",
  "mall-10000806": "戰術人形：AK-12",
  "mall-10000807": "戰術人形：AN-94",
  "mall-10000808": "戰術人形：MDR",
  "mall-10000809": "戰術人形：K11",
  "mall-10000810": "戰術人形：64式自",
  "mall-10000811": "戰術人形：ADS",
  "mall-10000812": "戰術人形：Kar98k",
  "mall-10000813": "戰術人形：WA2000",
  "mall-10000814": "戰術人形：李-恩菲爾德",
  "mall-10000815": "戰術人形：NTW-20",
  "mall-10000816": "戰術人形：M99",
  "mall-10000817": "戰術人形：IWS 2000",
  "mall-10000818": "戰術人形：卡爾卡諾M1891",
  "mall-10000819": "戰術人形：卡爾卡諾M91/38",
  "mall-10000820": "戰術人形：M200",
  "mall-10000821": "戰術人形：QBU-88",
  "mall-10000822": "戰術人形：湯姆森",
  "mall-10000823": "戰術人形：Vector",
  "mall-10000824": "戰術人形：G36C",
  "mall-10000825": "戰術人形：索米",
  "mall-10000826": "戰術人形：79式",
  "mall-10000827": "戰術人形：SR-3MP",
  "mall-10000828": "戰術人形：C-MS",
  "mall-10000829": "戰術人形：一〇〇式",
  "mall-10000830": "戰術人形：P90",
  "mall-10000831": "戰術人形：MP7",
  "mall-10000832": "戰術人形：灰熊MkⅤ",
  "mall-10000833": "戰術人形：M950A",
  "mall-10000834": "戰術人形：維爾德MkⅡ",
  "mall-10000835": "戰術人形：NZ75",
  "mall-10000836": "戰術人形：競爭者",
  "mall-10000837": "戰術人形：Px4 風暴",
  "mall-10000838": "戰術人形：PA-15",
  "mall-10000839": "戰術人形：CAWS",
  "mall-10000840": "戰術人形：DP-12",
  "mall-10000841": "戰術人形：C-93",
  "mall-10000842": "戰術人形：SIG-556",
  "mall-10000843": "頭像：真核面具紀念頭像·偏振光",
  "mall-10000844": "戰術人形:X95",
  "mall-10000845": "戰術人形:ACR",
  "mall-10000846": "戰術人形:沙漠之鷹",
  "mall-10000847": "戰術人形:Kord",
  "mall-10000848": "戰術人形:JS 9",
  "mall-10000849": "戰術人形:M1895 CB",
  "mall-10000850": "戰術人形:SPP-1",
  "mall-10000851": "戰術人形:M82",
  "mall-10000852": "戰術人形:CF05",
  "mall-10000853": "戰術人形:T-CMS",
  "mall-10000854": "戰術人形:K3",
  "mall-10000855": "戰術人形:VP70",
  "mall-10000856": "戰術人形:SIX12",
  "mall-10000857": "戰術人形:INSAS",
  "mall-10000858": "戰術人形:Zas M76",
  "mall-10000859": "蛋奶草莓芝士",
  "mall-10000860": "蛋奶草莓芝士",
  "mall-10000861": "人力半價禮包",
  "mall-10000862": "彈藥半價禮包",
  "mall-10000863": "口糧半價禮包",
  "mall-10000864": "零件半價禮包",
  "mall-10000865": "契約半價禮包",
  "mall-10000866": "重裝補給禮包",
  "mall-10000867": "金鼠獻瑞禮包",
  "mall-10000868": "每日特惠禮包",
  "mall-10000869": "2月特惠禮包",
  "mall-10000870": "JS 9-棣棠卿",
  "mall-10000871": "MG36-懸鈴緋",
  "mall-10001911": "清新短碎髮",
  "mall-10001912": "朝氣雙馬尾",
  "mall-10001920": "祈年頭飾",
  "mall-10001931": "守歲短褂",
  "mall-10001932": "賀年旗袍",
  "mall-10001940": "迎福飾物",
  "mall-10001951": "加厚長褲",
  "mall-10001952": "高跟單鞋",
  "mall-10000872": "人力半價禮包",
  "mall-10000873": "彈藥半價禮包",
  "mall-10000874": "口糧半價禮包",
  "mall-10000875": "零件半價禮包",
  "mall-10000876": "契約半價禮包",
  "mall-10000877": "甜蜜誓約禮包",
  "mall-10000878": "G11-福鼠懶春",
  "mall-10000879": "四式-花拍子",
  "mall-10000880": "每日特惠禮包",
  "mall-10000881": "3月特惠禮包",
  "mall-10000882": "妖精補給禮包",
  "mall-10000883": "灰熊MkⅤ-星夜落雨之時",
  "mall-10000884": "斯捷奇金-山茶小姐的特別服務",
  "mall-10000886": "裝扮：FNC - 草莓蛋糕與波斯花",
  "mall-10000887": "傢俱：婚紗展示櫃",
  "mall-10000888": "名片：時光之際",
  "mall-10000889": "背景：落暮之城",
  "mall-10000890": "頭像：沙弗萊少女",
  "mall-10000891": "頭像：記述魔眼",
  "mall-10000892": "裝備：BPR4 & SRM6",
  "mall-10000893": "採購幣",
  "mall-10000894": "作戰報告書",
  "mall-10000895": "特種作戰報告書",
  "mall-10000896": "蛋奶草莓芝士",
  "mall-10000897": "戰術人形:芭莉斯塔",
  "mall-10000898": "戰術人形:SRS",
  "mall-10000899": "戰術人形:AUG",
  "mall-10000900": "戰術人形:UMP40",
  "mall-10000901": "戰術人形:KLIN",
  "mall-10000902": "戰術人形:PP-19",
  "mall-10000903": "蛋奶草莓芝士",
  "mall-10000904": "蛋奶草莓芝士",
  "mall-10000905": "每日特惠禮包",
  "mall-10000906": "4月特惠禮包",
  "mall-10000907": "心智升級特惠",
  "mall-10000908": "AA-12-無煙棒棒糖",
  "mall-10000909": "融合勢力定向補給",
  "mall-10002111": "隨性短髮",
  "mall-10002112": "放鬆披肩髮",
  "mall-10002120": "助眠幫手",
  "mall-10002131": "絲質睡眠襯衫",
  "mall-10002132": "絲質家居長衣",
  "mall-10002140": "妙想軟枕",
  "mall-10002151": "絲質睡褲",
  "mall-10002152": "棉絨短襪",
  "mall-10000910": "每日特惠禮包",
  "mall-10000911": "5月特惠禮包",
  "mall-10000912": "人力半價禮包",
  "mall-10000913": "彈藥半價禮包",
  "mall-10000914": "口糧半價禮包",
  "mall-10000915": "零件半價禮包",
  "mall-10000916": "契約半價禮包",
  "mall-10000917": "戰術人形:KSVK",
  "mall-10000918": "戰術人形:M1887",
  "mall-10000919": "戰術人形:DSR-50",
  "mall-10000920": "戰術人形:M82A1",
  "mall-10000921": "戰術人形:TAC-50",
  "mall-10000922": "戰術人形:R93",
  "mall-10000923": "蛋奶草莓芝士",
  "mall-10000924": "蛋奶草莓芝士",
  "mall-10000925": "RO635-稻田裡的守護者",
  "mall-10000926": "HK416-千宵草味的錫紙糖",
  "mall-10000927": "G11-尋找勇氣的雷克斯兔",
  "mall-10000928": "AR15-飄向花海的禮帽",
  "mall-10000929": "M4 SOPMODII-被守護的寵愛者",
  "mall-10000930": "UMP45-逐願的禮花魔法師",
  "mall-10000931": "UMP9-償願的禮花魔法師",
  "mall-10000932": "M16A1-獨眼的白兔騎士",
  "mall-10000933": "UMP40-守望心願的暗影女巫",
  "mall-10000934": "人力半價禮包",
  "mall-10000935": "彈藥半價禮包",
  "mall-10000936": "口糧半價禮包",
  "mall-10000937": "零件半價禮包",
  "mall-10000938": "契約半價禮包",
  "mall-10000939": "重裝補給禮包",
  "mall-10000940": "融合勢力定向補給",
  "mall-10000941": "戰術人形：KSG",
  "mall-10000942": "戰術人形：Saiga-12",
  "mall-10000943": "戰術人形：AA-12",
  "mall-10000944": "戰術人形：FP-6",
  "mall-10000945": "戰術人形：S.A.T.8",
  "mall-10000946": "戰術人形：MG5",
  "mall-10000947": "戰術人形：內蓋夫",
  "mall-10000948": "戰術人形：MG4",
  "mall-10000949": "戰術人形：PKP",
  "mall-10000950": "戰術人形：88式",
  "mall-10000951": "戰術人形：MG36",
  "mall-10000952": "戰術人形：G41",
  "mall-10000953": "戰術人形：HK416",
  "mall-10000954": "戰術人形：FAL",
  "mall-10000955": "戰術人形：G11",
  "mall-10000956": "戰術人形：95式",
  "mall-10000957": "戰術人形：97式",
  "mall-10000958": "戰術人形：RFB",
  "mall-10000959": "戰術人形：T91",
  "mall-10000960": "戰術人形：K2",
  "mall-10000961": "戰術人形：Zas M21",
  "mall-10000962": "戰術人形：AK-12",
  "mall-10000963": "戰術人形：AN-94",
  "mall-10000964": "戰術人形：MDR",
  "mall-10000965": "戰術人形：K11",
  "mall-10000966": "戰術人形：64式自",
  "mall-10000967": "戰術人形：ADS",
  "mall-10000968": "戰術人形：Kar98k",
  "mall-10000969": "戰術人形：WA2000",
  "mall-10000970": "戰術人形：李-恩菲爾德",
  "mall-10000971": "戰術人形：NTW-20",
  "mall-10000972": "戰術人形：M99",
  "mall-10000973": "戰術人形：IWS 2000",
  "mall-10000974": "戰術人形：卡爾卡諾M1891",
  "mall-10000975": "戰術人形：卡爾卡諾M91/38",
  "mall-10000976": "戰術人形：M200",
  "mall-10000977": "戰術人形：QBU-88",
  "mall-10000978": "戰術人形：湯姆森",
  "mall-10000979": "戰術人形：Vector",
  "mall-10000980": "戰術人形：G36C",
  "mall-10000981": "戰術人形：索米",
  "mall-10000982": "戰術人形：79式",
  "mall-10000983": "戰術人形：SR-3MP",
  "mall-10000984": "戰術人形：C-MS",
  "mall-10000985": "戰術人形：一〇〇式",
  "mall-10000986": "戰術人形：P90",
  "mall-10000987": "戰術人形：MP7",
  "mall-10000988": "戰術人形：灰熊MkⅤ",
  "mall-10000989": "戰術人形：M950A",
  "mall-10000990": "戰術人形：維爾德MkⅡ",
  "mall-10000991": "戰術人形：NZ75",
  "mall-10000992": "戰術人形：競爭者",
  "mall-10000993": "戰術人形：Px4 風暴",
  "mall-10000994": "戰術人形：PA-15",
  "mall-10000995": "戰術人形：CAWS",
  "mall-10000996": "戰術人形：DP-12",
  "mall-10000997": "戰術人形：C-93",
  "mall-10000998": "戰術人形：SIG-556",
  "mall-10000999": "戰術人形：HP-35",
  "mall-10010000": "戰術人形：AK-15",
  "mall-10010001": "戰術人形：89式自",
  "mall-10010002": "戰術人形：AK-Alfa",
  "mall-10010003": "戰術人形：ZB-26",
  "mall-10010004": "戰術人形：RPK-16",
  "mall-10010005": "頭像：真核面具紀念頭像·4周年",
  "mall-10010006": "M200-戰地的採訪者",
  "mall-10010007": "RO635-規則的實行者",
  "mall-10010008": "ST AR-15-夢境的囚困者",
  "mall-10010009": "M4A1-時光的定格者",
  "mall-10010010": "M16A1-道路的指引者",
  "mall-10010011": "M4 SOPMODII-酒席的掃蕩者",
  "mall-10010012": "每日特惠禮包",
  "mall-10010013": "6月特惠禮包",
  "mall-10010014": "X95-白薔薇少女",
  "mall-10010015": "FAMAS-鳥與森語者",
  "mall-10010016": "融合勢力定向補給",
  "mall-10010017": "裝扮：阿斯特拉左輪-阿斯特拉的泳池漂流",
  "mall-10010018": "傢俱：沙灘王者",
  "mall-10010019": "名片：碧海BBQ",
  "mall-10010020": "頭像：熱帶莫吉托",
  "mall-10010021": "頭像：第51天的夕陽",
  "mall-10010022": "裝備：S&B762",
  "mall-10010023": "採購幣",
  "mall-10010024": "作戰報告書",
  "mall-10010025": "特種作戰報告書",
  "mall-10010026": "蛋奶草莓芝士",
  "mall-10010027": "戰術人形:Cx4 風暴",
  "mall-10010028": "戰術人形:OTs-14",
  "mall-10010029": "戰術人形:AK-74U",
  "mall-10010030": "戰術人形:X95",
  "mall-10010033": "蛋奶草莓芝士",
  "mall-10010034": "蛋奶草莓芝士",
  "mall-10010035": "每日特惠禮包",
  "mall-10010036": "7月特惠禮包",
  "mall-10010037": "人形：崔耶拉",
  "mall-10010038": "人形：黎各",
  "mall-10010039": "裝備：古董萬花筒",
  "mall-10010040": "裝備：決鬥撲克",
  "mall-10010041": "裝備：格鬥刀",
  "mall-10010042": "裝備：平光眼鏡",
  "mall-10010043": "裝備：天外隕石",
  "mall-10010044": "裝備：計時腕表",
  "mall-10010045": "裝備：童話繪本",
  "mall-10010046": "名片：萬願之核",
  "mall-10010047": "名片：疑慮之果",
  "mall-10010048": "頭像：舒緩香草",
  "mall-10010049": "頭像：少女們的魔法師",
  "mall-10010050": "頭像：甜點品鑑人",
  "mall-10010051": "頭像：沉睡的南瓜公主",
  "mall-10010052": "頭像：蜂蜜陽光",
  "mall-10010053": "家具：某人的小提琴",
  "mall-10010054": "訓練靶紙",
  "mall-10010055": "幸福魔法",
  "mall-10010056": "特種作戰報告書",
  "mall-10010057": "人形：克拉耶絲",
  "mall-10010058": "人形：安潔麗卡",
  "mall-10010059": "人形：CZ2000",
  "mall-10010060": "人形：JS 9",
  "mall-10010061": "人形：PM-9",
  "mall-10010062": "蛋奶草莓芝士",
  "mall-10010063": "蛋奶草莓芝士",
  "mall-10010064": "盛夏限定禮包",
  "mall-10010065": "融合勢力養成禮包",
  "mall-10010066": "融合勢力定向補給",
  "mall-10010067": "夢間劇特惠",
  "mall-10010068": "夢間劇限定",
  "mall-10010069": "崔耶拉-暗影行動",
  "mall-10010070": "黎各-自由餐廳",
  "mall-10010071": "荷莉葉特-月神假日",
  "mall-10010072": "克拉耶絲-晨風庭園",
  "mall-10010073": "安潔麗卡-童話起點",
  "mall-10010074": "KAC-PDW-甜慕之心",
  "mall-10010075": "SL8-怒濤之巔",
  "mall-10010076": "每日特惠禮包",
  "mall-10010077": "8月特惠禮包",
  "mall-10010078": "人力半價禮包",
  "mall-10010079": "彈藥半價禮包",
  "mall-10010080": "口糧半價禮包",
  "mall-10010081": "零件半價禮包",
  "mall-10010082": "契約半價禮包",
  "mall-10010083": "融合勢力養成禮包",
  "mall-10010084": "融合勢力定向補給",
  "mall-10010085": "心智升級特惠",
  "mall-10010086": "七夕特惠禮包",
  "mall-10010087": "戰術人形：KSG",
  "mall-10010088": "戰術人形：Saiga-12",
  "mall-10010089": "戰術人形：AA-12",
  "mall-10010090": "戰術人形：FP-6",
  "mall-10010091": "戰術人形：S.A.T.8",
  "mall-10010092": "戰術人形：MG5",
  "mall-10010093": "戰術人形：內蓋夫",
  "mall-10010094": "戰術人形：MG4",
  "mall-10010095": "戰術人形：PKP",
  "mall-10010096": "戰術人形：88式",
  "mall-10010097": "戰術人形：MG36",
  "mall-10010098": "戰術人形：G41",
  "mall-10010099": "戰術人形：HK416",
  "mall-10010100": "戰術人形：FAL",
  "mall-10010101": "戰術人形：G11",
  "mall-10010102": "戰術人形：95式",
  "mall-10010103": "戰術人形：97式",
  "mall-10010104": "戰術人形：RFB",
  "mall-10010105": "戰術人形：T91",
  "mall-10010106": "戰術人形：K2",
  "mall-10010107": "戰術人形：Zas M21",
  "mall-10010108": "戰術人形：AK-12",
  "mall-10010109": "戰術人形：AN-94",
  "mall-10010110": "戰術人形：MDR",
  "mall-10010111": "戰術人形：K11",
  "mall-10010112": "戰術人形：64式自",
  "mall-10010113": "戰術人形：ADS",
  "mall-10010114": "戰術人形：Kar98k",
  "mall-10010115": "戰術人形：WA2000",
  "mall-10010116": "戰術人形：李-恩菲爾德",
  "mall-10010117": "戰術人形：NTW-20",
  "mall-10010118": "戰術人形：M99",
  "mall-10010119": "戰術人形：IWS 2000",
  "mall-10010120": "戰術人形：卡爾卡諾M1891",
  "mall-10010121": "戰術人形：卡爾卡諾M91/38",
  "mall-10010122": "戰術人形：M200",
  "mall-10010123": "戰術人形：QBU-88",
  "mall-10010124": "戰術人形：湯姆森",
  "mall-10010125": "戰術人形：Vector",
  "mall-10010126": "戰術人形：G36C",
  "mall-10010127": "戰術人形：索米",
  "mall-10010128": "戰術人形：79式",
  "mall-10010129": "戰術人形：SR-3MP",
  "mall-10010130": "戰術人形：C-MS",
  "mall-10010131": "戰術人形：一〇〇式",
  "mall-10010132": "戰術人形：P90",
  "mall-10010133": "戰術人形：MP7",
  "mall-10010134": "戰術人形：灰熊MkⅤ",
  "mall-10010135": "戰術人形：M950A",
  "mall-10010136": "戰術人形：維爾德MkⅡ",
  "mall-10010137": "戰術人形：NZ75",
  "mall-10010138": "戰術人形：競爭者",
  "mall-10010139": "戰術人形：Px4 風暴",
  "mall-10010140": "戰術人形：PA-15",
  "mall-10010141": "戰術人形：CAWS",
  "mall-10010142": "戰術人形：DP-12",
  "mall-10010143": "戰術人形：C-93",
  "mall-10010144": "戰術人形：SIG-556",
  "mall-10010145": "戰術人形：HP-35",
  "mall-10010146": "戰術人形：AK-15",
  "mall-10010147": "戰術人形：89式自",
  "mall-10010148": "戰術人形：AK-Alfa",
  "mall-10010149": "戰術人形：ZB-26",
  "mall-10010150": "戰術人形：RPK-16",
  "mall-10010151": "戰術人形：VSK-94",
  "mall-10010152": "戰術人形：S-ACR",
  "mall-10010153": "頭像：真核面具紀念頭像·雙聯亂數",
  "mall-10010154": "戰術人形:蒙德拉貢M1908",
  "mall-10010155": "戰術人形:劉氏步槍",
  "mall-10010156": "戰術人形:Five-seveN",
  "mall-10010157": "戰術人形:蜜獾",
  "mall-10010158": "戰術人形:ART556",
  "mall-10010159": "戰術人形:JS05",
  "mall-10010160": "戰術人形:M82",
  "mall-10010161": "戰術人形:沙漠之鷹",
  "mall-10010162": "戰術人形:HS2000",
  "mall-10010163": "戰術人形:43M",
  "mall-10010164": "戰術人形:Vepr",
  "mall-10010165": "戰術人形:高標10型",
  "mall-10010166": "戰術人形:CAR",
  "mall-10010167": "戰術人形:MAS-38",
  "mall-10010168": "戰術人形:C14",
  "mall-10010169": "蛋奶草莓芝士",
  "mall-10010170": "蛋奶草莓芝士",
  "mall-10010171": "夏日補給禮包",
  "mall-10010172": "每日特惠禮包",
  "mall-10010173": "9月特惠禮包",
  "mall-10002611": "方便短髮",
  "mall-10002612": "克己束髮",
  "mall-10002620": "血火飾品",
  "mall-10002631": "守護者戰衣",
  "mall-10002632": "宣誓者戰衣",
  "mall-10002640": "貼身武器",
  "mall-10002651": "守護者鎧靴",
  "mall-10002652": "宣誓者鎧靴",
  "mall-10010174": "融合勢力養成禮包",
  "mall-10010175": "融合勢力定向補給",
  "mall-10010176": "MG36-竹影清兵衛",
  "mall-10010177": "塔布克-食魂料理人",
  "mall-10002711": "浪客馬尾",
  "mall-10002712": "持家馬尾",
  "mall-10002720": "吟風者",
  "mall-10002731": "執勤者制服",
  "mall-10002732": "迎客新裙裝",
  "mall-10002740": "信念幟旗",
  "mall-10002751": "威嚴長袴",
  "mall-10002752": "便捷木屐",
  "mall-10010178": "戰術人形:SPP-1",
  "mall-10010179": "戰術人形:UKM-2000",
  "mall-10010180": "戰術人形:HK21",
  "mall-10010181": "戰術人形:路易士",
  "mall-10010182": "戰術人形:P22",
  "mall-10010183": "戰術人形:R93",
  "mall-10010184": "蛋奶草莓芝士",
  "mall-10010185": "蛋奶草莓芝士",
  "mall-10010186": "每日特惠禮包",
  "mall-10010187": "10月特惠禮包",
  "mall-10010188": "人力半價禮包",
  "mall-10010189": "彈藥半價禮包",
  "mall-10010190": "口糧半價禮包",
  "mall-10010191": "零件半價禮包",
  "mall-10010192": "契約半價禮包",
  "mall-10010193": "融合勢力養成禮包",
  "mall-10010194": "融合勢力定向補給",
  "mall-10010195": "重裝補給禮包",
  "mall-10010196": "戰術人形:KSVK",
  "mall-10010197": "戰術人形:CZ2000",
  "mall-10010198": "戰術人形:蜜獾",
  "mall-10010199": "戰術人形:P22",
  "mall-10010200": "蛋奶草莓芝士",
  "mall-10010201": "蛋奶草莓芝士",
  "mall-10010202": "人形培養禮包",
  "mall-10010203": "每日特惠禮包",
  "mall-10010204": "11月特惠禮包",
  "mall-10010205": "雙11特供禮包",
  "mall-10010206": "雙11尊享禮包",
  "mall-10010207": "雙11訓練特惠",
  "mall-10010208": "裝扮：托卡列夫-甜夜盜賊",
  "mall-10010209": "傢俱：招魂嬰兒車",
  "mall-10010210": "指揮官頭飾：魔物統領",
  "mall-10010211": "名片：謝幕之時",
  "mall-10010212": "頭像：沉默訣別",
  "mall-10010213": "頭像：假面人生",
  "mall-10010214": "裝備：木製握把片",
  "mall-10010215": "採購幣",
  "mall-10010216": "作戰報告書",
  "mall-10010217": "特種作戰報告書",
  "mall-10010218": "蛋奶草莓芝士",
  "mall-10010219": "戰術人形:Kord",
  "mall-10010220": "戰術人形:韋伯利",
  "mall-10010221": "戰術人形:CF05",
  "mall-10010222": "蛋奶草莓芝士",
  "mall-10010223": "蛋奶草莓芝士",
  "mall-10010224": "融合勢力養成禮包",
  "mall-10010225": "融合勢力定向補給",
  "mall-10010226": "97式-魔女格萊特",
  "mall-10010227": "人力半價禮包",
  "mall-10010228": "彈藥半價禮包",
  "mall-10010229": "口糧半價禮包",
  "mall-10010230": "零件半價禮包",
  "mall-10010231": "契約半價禮包",
  "mall-10010232": "人形:特工416",
  "mall-10010233": "特工Vector專屬:.45空尖彈（燃燒）",
  "mall-10010234": "特工416專屬:556高速彈（爆破）",
  "mall-10010235": "名片:明日之都",
  "mall-10010236": "名片:曙光",
  "mall-10010259": "名片:靜謐冷舍",
  "mall-10010237": "背景:藏身處",
  "mall-10010238": "頭像:原罪·利維坦",
  "mall-10010239": "頭像:「指揮官在格里芬」",
  "mall-10010260": "頭像:特工「蒂瑪」",
  "mall-10010240": "傢俱:加密貯藏箱",
  "mall-10010241": "傢俱:「此路不通」",
  "mall-10010242": "坎德爾制劑",
  "mall-10010243": "威士忌",
  "mall-10010244": "採購幣",
  "mall-10010245": "特種作戰報告書",
  "mall-10010246": "戰術人形:M1895 CB",
  "mall-10010247": "戰術人形:SSG3000",
  "mall-10010248": "戰術人形:ACR",
  "mall-10010249": "戰術人形:R5",
  "mall-10010250": "戰術人形:PM-06",
  "mall-10010251": "蛋奶草莓芝士",
  "mall-10010252": "蛋奶草莓芝士",
  "mall-10010253": "每日特惠禮包",
  "mall-10010254": "12月特惠禮包",
  "mall-10010255": "VHS-第八頁守密人",
  "mall-10010256": "融合勢力養成禮包",
  "mall-10010257": "融合勢力定向補給",
  "mall-10010258": "黑五特供",
  "mall-10003011": "髮廊爆款短髮",
  "mall-10003012": "傳統簡便編髮",
  "mall-10003020": "頭部防風設備",
  "mall-10003031": "戰術衝鋒衣（袖章款）",
  "mall-10003032": "戰術衝鋒衣（印花款）",
  "mall-10003040": "背掛式戰術裝備",
  "mall-10003051": "特種作戰下裝（制服款）",
  "mall-10003052": "特種作戰下裝（牛仔款）",
  "mall-10010261": "心智升級特惠",
  "mall-10010262": "聖誕特惠禮包",
  "mall-10010263": "聖誕定向補給",
  "mall-10010264": "聖誕限定",
  "mall-10010265": "聖誕特供",
  "mall-10010266": "每日特惠禮包",
  "mall-10010267": "元旦特惠",
  "mall-10010268": "元旦限定",
  "mall-10010269": "元旦尊享",
  "mall-10010270": "K5-拾願者K德瑞拉",
  "mall-10010271": "HS2000-燃心鐵皮人",
  "mall-10010272": "PM1910-女王的高塔派對",
  "mall-10010273": "融合勢力養成禮包",
  "mall-10010274": "融合勢力定向補給",
  "mall-10010275": "戰術人形:HK21",
  "mall-10010276": "戰術人形:路易士",
  "mall-10010277": "戰術人形:HS2000",
  "mall-10010278": "戰術人形:UKM-2000",
  "mall-10010279": "蛋奶草莓芝士",
  "mall-10010280": "蛋奶草莓芝士",
  "mall-10010281": "人力半價禮包",
  "mall-10010282": "彈藥半價禮包",
  "mall-10010283": "口糧半價禮包",
  "mall-10010284": "零件半價禮包",
  "mall-10010285": "契約半價禮包",
  "mall-10010286": "ACR-藍黎軟香",
  "mall-10010287": "UKM-2000-冬原宅急便",
  "mall-10010288": "希普卡-新詩譜寫時",
  "mall-10010289": "融合勢力養成禮包",
  "mall-10010290": "融合勢力定向補給",
  "mall-10010291": "每日特惠禮包",
  "mall-10010292": "2月特惠禮包",
  "mall-10010293": "鏡像論備戰補給",
  "mall-10010294": "鏡像論訓練補給",
  "mall-10010295": "鏡像論重裝補給",
  "mall-10010296": "人力半價禮包",
  "mall-10010297": "彈藥半價禮包",
  "mall-10010298": "口糧半價禮包",
  "mall-10010299": "零件半價禮包",
  "mall-10010300": "契約半價禮包",
  "mall-10010301": "融合勢力養成禮包",
  "mall-10010302": "融合勢力定向補給",
  "mall-10010303": "重裝補給禮包",
  "mall-10010304": "心智升級特惠",
  "mall-10010305": "牛氣沖天",
  "mall-10010306": "牛運亨通",
  "mall-10010307": "牛轉乾坤",
  "mall-10010308": "AUG Para-聚瑤芳",
  "mall-10010309": "SVD-待月丹",
  "mall-10010310": "甜蜜誓約禮包",
  "mall-10010311": "融合勢力定向補給",
  "mall-10010312": "每日特惠禮包",
  "mall-10010313": "3月特惠禮包",
  "mall-10010314": "戰術人形：德林加",
  "mall-10010315": "戰術人形：Savage 99",
  "mall-10010316": "戰術人形：SL8",
  "mall-10010317": "戰術人形：CZ75",
  "mall-10010318": "戰術人形：Cx4風暴",
  "mall-10010319": "戰術人形：KSVK",
  "mall-10010320": "戰術人形：M1887",
  "mall-10010321": "戰術人形：路易士",
  "mall-10010322": "戰術人形：AUG Para",
  "mall-10010323": "戰術人形：WKp",
  "mall-10010324": "戰術人形：StG-940",
  "mall-10010325": "戰術人形：GM6 Lynx",
  "mall-10010326": "戰術人形：TS12",
  "mall-10010327": "戰術人形：QSB-91",
  "mall-10010328": "戰術人形：SUB-2000",
  "mall-10010329": "蛋奶草莓芝士",
  "mall-10010330": "蛋奶草莓芝士",
  "mall-10010331": "戰術人形：KSG",
  "mall-10010332": "戰術人形：Saiga-12",
  "mall-10010333": "戰術人形：AA-12",
  "mall-10010334": "戰術人形：FP-6",
  "mall-10010335": "戰術人形：S.A.T.8",
  "mall-10010336": "戰術人形：MG5",
  "mall-10010337": "戰術人形：內蓋夫",
  "mall-10010338": "戰術人形：MG4",
  "mall-10010339": "戰術人形：PKP",
  "mall-10010340": "戰術人形：88式",
  "mall-10010341": "戰術人形：MG36",
  "mall-10010342": "戰術人形：G41",
  "mall-10010343": "戰術人形：HK416",
  "mall-10010344": "戰術人形：FAL",
  "mall-10010345": "戰術人形：G11",
  "mall-10010346": "戰術人形：95式",
  "mall-10010347": "戰術人形：97式",
  "mall-10010348": "戰術人形：RFB",
  "mall-10010349": "戰術人形：T91",
  "mall-10010350": "戰術人形：K2",
  "mall-10010351": "戰術人形：Zas M21",
  "mall-10010352": "戰術人形：AK-12",
  "mall-10010353": "戰術人形：AN-94",
  "mall-10010354": "戰術人形：MDR",
  "mall-10010355": "戰術人形：K11",
  "mall-10010356": "戰術人形：64式自",
  "mall-10010357": "戰術人形：ADS",
  "mall-10010358": "戰術人形：Kar98k",
  "mall-10010359": "戰術人形：WA2000",
  "mall-10010360": "戰術人形：李-恩菲爾德",
  "mall-10010361": "戰術人形：NTW-20",
  "mall-10010362": "戰術人形：M99",
  "mall-10010363": "戰術人形：IWS 2000",
  "mall-10010364": "戰術人形：卡爾卡諾M1891",
  "mall-10010365": "戰術人形：卡爾卡諾M91/38",
  "mall-10010366": "戰術人形：M200",
  "mall-10010367": "戰術人形：QBU-88",
  "mall-10010368": "戰術人形：湯姆森",
  "mall-10010369": "戰術人形：Vector",
  "mall-10010370": "戰術人形：G36C",
  "mall-10010371": "戰術人形：索米",
  "mall-10010372": "戰術人形：79式",
  "mall-10010373": "戰術人形：SR-3MP",
  "mall-10010374": "戰術人形：C-MS",
  "mall-10010375": "戰術人形：一〇〇式",
  "mall-10010376": "戰術人形：P90",
  "mall-10010377": "戰術人形：MP7",
  "mall-10010378": "戰術人形：灰熊MkⅤ",
  "mall-10010379": "戰術人形：M950A",
  "mall-10010380": "戰術人形：維爾德MkⅡ",
  "mall-10010381": "戰術人形：NZ75",
  "mall-10010382": "戰術人形：競爭者",
  "mall-10010383": "戰術人形：Px4 風暴",
  "mall-10010384": "戰術人形：PA-15",
  "mall-10010385": "戰術人形：CAWS",
  "mall-10010386": "戰術人形：DP-12",
  "mall-10010387": "戰術人形：C-93",
  "mall-10010388": "戰術人形：SIG-556",
  "mall-10010389": "戰術人形：HP-35",
  "mall-10010390": "戰術人形：AK-15",
  "mall-10010391": "戰術人形：89式自",
  "mall-10010392": "戰術人形：AK-Alfa",
  "mall-10010393": "戰術人形：ZB-26",
  "mall-10010394": "戰術人形：RPK-16",
  "mall-10010395": "戰術人形：VSK-94",
  "mall-10010396": "戰術人形：S-ACR",
  "mall-10010397": "戰術人形：LTLX7000",
  "mall-10010398": "戰術人形：M6 ASW",
  "mall-10010399": "戰術人形：SVCh",
  "mall-10010400": "頭像：真核面具紀念頭像·鏡像論",
  "mall-10010401": "融合勢力養成禮包",
  "mall-10010402": "融合勢力定向補給",
  "mall-10010403": "95式-洋桔梗與她的季節",
  "mall-10010404": "韋伯利-日落黃昏時",
  "mall-10010405": "甜蜜誓約禮包",
  "mall-10010406": "人力半價禮包",
  "mall-10010407": "彈藥半價禮包",
  "mall-10010408": "口糧半價禮包",
  "mall-10010409": "零件半價禮包",
  "mall-10010410": "契約半價禮包",
  "mall-10010411": "每日特惠禮包",
  "mall-10010412": "4月特惠禮包",
  "mall-10010413": "融合勢力定向補給",
  "mall-10010414": "融合勢力養成禮包",
  "mall-10010415": "融合勢力定向補給",
  "mall-10010416": "蒙德拉貢M1908-宿命的修護者",
  "mall-10003411": "紳士禮堂",
  "mall-10003412": "淑女桂苑",
  "mall-10003420": "英倫風範",
  "mall-10003431": "泰晤士風衣（男）",
  "mall-10003432": "泰晤士風衣（女）",
  "mall-10003440": "探員搭檔",
  "mall-10003451": "歐式西褲",
  "mall-10003452": "歐式褲襪",
  "mall-10010417": "每日特惠禮包",
  "mall-10010418": "5月特惠禮包",
  "mall-10010419": "戰術人形:蒙德拉貢M1908",
  "mall-10010420": "戰術人形:DSR-50",
  "mall-10010421": "戰術人形:M82A1",
  "mall-10010422": "戰術人形:TAC-50",
  "mall-10010423": "戰術人形:PM-9",
  "mall-10010424": "戰術人形:劉氏步槍",
  "mall-10010425": "蛋奶草莓芝士",
  "mall-10010426": "蛋奶草莓芝士",
  "mall-10010427": "融合勢力定向補給",
  "mall-10010428": "心智升級特惠",
  "mall-10010429": "戰術人形：KSG",
  "mall-10010430": "戰術人形：Saiga-12",
  "mall-10010431": "戰術人形：AA-12",
  "mall-10010432": "戰術人形：FP-6",
  "mall-10010433": "戰術人形：S.A.T.8",
  "mall-10010434": "戰術人形：MG5",
  "mall-10010435": "戰術人形：內蓋夫",
  "mall-10010436": "戰術人形：MG4",
  "mall-10010437": "戰術人形：PKP",
  "mall-10010438": "戰術人形：88式",
  "mall-10010439": "戰術人形：MG36",
  "mall-10010440": "戰術人形：G41",
  "mall-10010441": "戰術人形：HK416",
  "mall-10010442": "戰術人形：FAL",
  "mall-10010443": "戰術人形：G11",
  "mall-10010444": "戰術人形：95式",
  "mall-10010445": "戰術人形：97式",
  "mall-10010446": "戰術人形：RFB",
  "mall-10010447": "戰術人形：T91",
  "mall-10010448": "戰術人形：K2",
  "mall-10010449": "戰術人形：Zas M21",
  "mall-10010450": "戰術人形：AK-12",
  "mall-10010451": "戰術人形：AN-94",
  "mall-10010452": "戰術人形：MDR",
  "mall-10010453": "戰術人形：K11",
  "mall-10010454": "戰術人形：64式自",
  "mall-10010455": "戰術人形：ADS",
  "mall-10010456": "戰術人形：Kar98k",
  "mall-10010457": "戰術人形：WA2000",
  "mall-10010458": "戰術人形：李-恩菲爾德",
  "mall-10010459": "戰術人形：NTW-20",
  "mall-10010460": "戰術人形：M99",
  "mall-10010461": "戰術人形：IWS 2000",
  "mall-10010462": "戰術人形：卡爾卡諾M1891",
  "mall-10010463": "戰術人形：卡爾卡諾M91/38",
  "mall-10010464": "戰術人形：M200",
  "mall-10010465": "戰術人形：QBU-88",
  "mall-10010466": "戰術人形：湯姆森",
  "mall-10010467": "戰術人形：Vector",
  "mall-10010468": "戰術人形：G36C",
  "mall-10010469": "戰術人形：索米",
  "mall-10010470": "戰術人形：79式",
  "mall-10010471": "戰術人形：SR-3MP",
  "mall-10010472": "戰術人形：C-MS",
  "mall-10010473": "戰術人形：一〇〇式",
  "mall-10010474": "戰術人形：P90",
  "mall-10010475": "戰術人形：MP7",
  "mall-10010476": "戰術人形：灰熊MkⅤ",
  "mall-10010477": "戰術人形：M950A",
  "mall-10010478": "戰術人形：維爾德MkⅡ",
  "mall-10010479": "戰術人形：NZ75",
  "mall-10010480": "戰術人形：競爭者",
  "mall-10010481": "戰術人形：Px4 風暴",
  "mall-10010482": "戰術人形：PA-15",
  "mall-10010483": "戰術人形：CAWS",
  "mall-10010484": "戰術人形：DP-12",
  "mall-10010485": "戰術人形：C-93",
  "mall-10010486": "戰術人形：SIG-556",
  "mall-10010487": "戰術人形：HP-35",
  "mall-10010488": "戰術人形：AK-15",
  "mall-10010489": "戰術人形：89式自",
  "mall-10010490": "戰術人形：AK-Alfa",
  "mall-10010491": "戰術人形：ZB-26",
  "mall-10010492": "戰術人形：RPK-16",
  "mall-10010493": "戰術人形：VSK-94",
  "mall-10010494": "戰術人形：S-ACR",
  "mall-10010495": "戰術人形：LTLX7000",
  "mall-10010496": "戰術人形：M6 ASW",
  "mall-10010497": "戰術人形：SVCh",
  "mall-10010498": "戰術人形：RPK-203",
  "mall-10010499": "戰術人形：SIG MCX",
  "mall-10010500": "戰術人形：德利爾",
  "mall-10010501": "頭像：真核面具紀念頭像·五周年",
  "mall-10010502": "VHS-諧謔天鵝湖",
  "mall-10010503": "SL8-即興狂想樂",
  "mall-10010504": "G36-光輝守望者",
  "mall-10010505": "M200-莊嚴行進",
  "mall-10010506": "M82A1-來自闇冥",
  "mall-10010507": "人力半價禮包",
  "mall-10010508": "彈藥半價禮包",
  "mall-10010509": "口糧半價禮包",
  "mall-10010510": "零件半價禮包",
  "mall-10010511": "契約半價禮包",
  "mall-10010512": "重裝補給禮包",
  "mall-10010513": "VSK-94-銀灣流轉夜",
  "mall-10010514": "每日特惠禮包",
  "mall-10010515": "6月特惠禮包",
  "mall-10010516": "融合勢力定向補給",
  "mall-10010517": "裝扮：V-PM5-飛翔海星",
  "mall-10010518": "傢俱：蔚藍邊際",
  "mall-10010519": "名片：浴光沐影",
  "mall-10010520": "頭像：捩浪人",
  "mall-10010521": "頭像：來自深海",
  "mall-10010522": "頭像：影后",
  "mall-10010523": "裝備：液壓系統後托",
  "mall-10010524": "採購幣",
  "mall-10010525": "作戰報告書",
  "mall-10010526": "特種作戰報告書",
  "mall-10010527": "蛋奶草莓芝士",
  "mall-10010528": "戰術人形:CF05",
  "mall-10010529": "戰術人形:M82",
  "mall-10010530": "戰術人形:JS9",
  "mall-10010531": "戰術人形:Lusa",
  "mall-10010532": "蛋奶草莓芝士",
  "mall-10010533": "蛋奶草莓芝士",
  "mall-10010534": "Lusa兒童節裝扮禮包",
  "mall-10010535": "AK5兒童節裝扮禮包",
  "mall-10010536": "wz.29兒童節裝扮禮包",
  "mall-10010537": "每日特惠禮包",
  "mall-10010538": "7月特惠禮包",
  "mall-10010568": "融合勢力定向補給",
  "mall-10010569": "PPD-40-櫻桃色珊瑚",
  "mall-10010570": "QSB-91-浮水薄荷茶",
  "mall-10010571": "小邪神-墨鴿爵士",
  "mall-10010572": "花園百合鈴-惡魔在身邊",
  "mall-10010573": "梅杜莎-濃情生巧職人",
  "mall-10010574": "佩珂拉-打工吧！天使大人",
  "mall-10010575": "米諾斯-湖畔對飲夜",
  "mall-10010576": "融合勢力定向補給",
  "mall-10010539": "人形：小邪神",
  "mall-10010540": "人形：花園百合鈴",
  "mall-10010541": "裝備：奇蹟咖哩勺",
  "mall-10010542": "裝備：魔導書下冊",
  "mall-10010543": "裝備：紙袋頭盔",
  "mall-10010544": "裝備：搖擺魔鈴",
  "mall-10010545": "裝備：美夢甜甜圈",
  "mall-10010546": "名片背景：溫情四疊半",
  "mall-10010547": "基地背景：夢始之地",
  "mall-10010548": "基地背景：約定的飯店夢",
  "mall-10010549": "頭像：一瞥知其心",
  "mall-10010550": "頭像：一筷嚐冷暖",
  "mall-10010551": "頭像：一嗅思摯友",
  "mall-10010552": "頭像：惡魔的呼喚",
  "mall-10010553": "妖精：浩二",
  "mall-10010554": "寵物：小單眼",
  "mall-10010555": "傢俱：邪神畫像",
  "mall-10010556": "傢俱：基本款魔毯",
  "mall-10010557": "撒旦之淚",
  "mall-10010558": "伊甸蘋果",
  "mall-10010559": "人形:梅杜莎",
  "mall-10010560": "人形:米諾斯",
  "mall-10010561": "戰術人形:Five-seveN",
  "mall-10010562": "戰術人形:JS05",
  "mall-10010563": "戰術人形:ART556",
  "mall-10010564": "戰術人形:UKM-2000",
  "mall-10010565": "戰術人形:沙漠之鷹",
  "mall-10010566": "蛋奶草莓芝士",
  "mall-10010567": "蛋奶草莓芝士",
  "mall-10010577": "每日特惠禮包",
  "mall-10010578": "8月特惠禮包",
  "mall-10010579": "融合勢力定向補給",
  "mall-10010580": "七夕特惠禮包",
  "mall-10010581": "戰術人形：KH2002",
  "mall-10010582": "戰術人形：FARA 83",
  "mall-10010583": "戰術人形：SPP-1",
  "mall-10010584": "戰術人形：PM1910",
  "mall-10010585": "戰術人形：VHS",
  "mall-10010586": "戰術人形：R5",
  "mall-10010587": "戰術人形：R93",
  "mall-10010588": "戰術人形：ACR",
  "mall-10010589": "蛋奶草莓芝士",
  "mall-10010590": "蛋奶草莓芝士",
  "mall-10010591": "戰術人形：KSG",
  "mall-10010592": "戰術人形：Saiga-12",
  "mall-10010593": "戰術人形：AA-12",
  "mall-10010594": "戰術人形：FP-6",
  "mall-10010595": "戰術人形：S.A.T.8",
  "mall-10010596": "戰術人形：MG5",
  "mall-10010597": "戰術人形：內蓋夫",
  "mall-10010598": "戰術人形：MG4",
  "mall-10010599": "戰術人形：PKP",
  "mall-10010600": "戰術人形：88式",
  "mall-10010601": "戰術人形：MG36",
  "mall-10010602": "戰術人形：G41",
  "mall-10010603": "戰術人形：HK416",
  "mall-10010604": "戰術人形：FAL",
  "mall-10010605": "戰術人形：G11",
  "mall-10010606": "戰術人形：95式",
  "mall-10010607": "戰術人形：97式",
  "mall-10010608": "戰術人形：RFB",
  "mall-10010609": "戰術人形：T91",
  "mall-10010610": "戰術人形：K2",
  "mall-10010611": "戰術人形：Zas M21",
  "mall-10010612": "戰術人形：AK-12",
  "mall-10010613": "戰術人形：AN-94",
  "mall-10010614": "戰術人形：MDR",
  "mall-10010615": "戰術人形：K11",
  "mall-10010616": "戰術人形：64式自",
  "mall-10010617": "戰術人形：ADS",
  "mall-10010618": "戰術人形：Kar98k",
  "mall-10010619": "戰術人形：WA2000",
  "mall-10010620": "戰術人形：李-恩菲爾德",
  "mall-10010621": "戰術人形：NTW-20",
  "mall-10010622": "戰術人形：M99",
  "mall-10010623": "戰術人形：IWS 2000",
  "mall-10010624": "戰術人形：卡爾卡諾M1891",
  "mall-10010625": "戰術人形：卡爾卡諾M91/38",
  "mall-10010626": "戰術人形：M200",
  "mall-10010627": "戰術人形：QBU-88",
  "mall-10010628": "戰術人形：湯姆森",
  "mall-10010629": "戰術人形：Vector",
  "mall-10010630": "戰術人形：G36C",
  "mall-10010631": "戰術人形：索米",
  "mall-10010632": "戰術人形：79式",
  "mall-10010633": "戰術人形：SR-3MP",
  "mall-10010634": "戰術人形：C-MS",
  "mall-10010635": "戰術人形：一〇〇式",
  "mall-10010636": "戰術人形：P90",
  "mall-10010637": "戰術人形：MP7",
  "mall-10010638": "戰術人形：灰熊MkⅤ",
  "mall-10010639": "戰術人形：M950A",
  "mall-10010640": "戰術人形：維爾德MkⅡ",
  "mall-10010641": "戰術人形：NZ75",
  "mall-10010642": "戰術人形：競爭者",
  "mall-10010643": "戰術人形：Px4 風暴",
  "mall-10010644": "戰術人形：PA-15",
  "mall-10010645": "戰術人形：CAWS",
  "mall-10010646": "戰術人形：DP-12",
  "mall-10010647": "戰術人形：C-93",
  "mall-10010648": "戰術人形：SIG-556",
  "mall-10010649": "戰術人形：HP-35",
  "mall-10010650": "戰術人形：AK-15",
  "mall-10010651": "戰術人形：89式自",
  "mall-10010652": "戰術人形：AK-Alfa",
  "mall-10010653": "戰術人形：ZB-26",
  "mall-10010654": "戰術人形：RPK-16",
  "mall-10010655": "戰術人形：VSK-94",
  "mall-10010656": "戰術人形：S-ACR",
  "mall-10010657": "戰術人形：LTLX7000",
  "mall-10010658": "戰術人形：M6 ASW",
  "mall-10010659": "戰術人形：SVCh",
  "mall-10010660": "戰術人形：RPK-203",
  "mall-10010661": "戰術人形：SIG MCX",
  "mall-10010662": "戰術人形：德利爾",
  "mall-10010663": "頭像：真核面具紀念頭像·熵減焓增",
  "mall-10010664": "每日特惠禮包",
  "mall-10010665": "9月特惠禮包",
  "mall-10010666": "融合勢力定向補給",
  "mall-10010667": "塔布克-三隻小豬來租房",
  "mall-10003911": "獨行孤狼",
  "mall-10003912": "迷途羔羊",
  "mall-10003920": "氣氛組飾品",
  "mall-10003931": "「夜行者」夾克",
  "mall-10003932": "「祈禱者」夾克",
  "mall-10003940": "遊樂贈禮",
  "mall-10003951": "「夜行者」長褲",
  "mall-10003952": "「祈禱者」短褲",
  "mall-10010668": "戰術人形:SSG3000",
  "mall-10010669": "戰術人形:蒙德拉貢M1908",
  "mall-10010670": "戰術人形:M1895 CB",
  "mall-10010671": "戰術人形:PM-06",
  "mall-10010672": "戰術人形:SL8",
  "mall-10010673": "戰術人形:AUG Para",
  "mall-10010674": "蛋奶草莓芝士",
  "mall-10010675": "蛋奶草莓芝士",
  "mall-10010676": "人力半價禮包",
  "mall-10010677": "彈藥半價禮包",
  "mall-10010678": "口糧半價禮包",
  "mall-10010679": "零件半價禮包",
  "mall-10010680": "契約半價禮包",
  "mall-10010681": "人力半價禮包",
  "mall-10010682": "彈藥半價禮包",
  "mall-10010683": "口糧半價禮包",
  "mall-10010684": "零件半價禮包",
  "mall-10010685": "契約半價禮包",
  "mall-10010686": "蒙德拉貢M1908-殘雨暝煙",
  "mall-10010687": "每日特惠禮包",
  "mall-10010688": "黃金週特惠",
  "mall-10010689": "黃金週補給",
  "mall-10010690": "重裝補給禮包",
  "mall-10004011": "少年的青澀",
  "mall-10004012": "少女的羞怯",
  "mall-10004020": "決勝戎裝",
  "mall-10004031": "沒捨得拆的新西裝",
  "mall-10004032": "剛剛選好的連衣裙",
  "mall-10004040": "回憶的贈禮",
  "mall-10004051": "沒捨得拆的新西褲",
  "mall-10004052": "剛剛選好的小皮鞋",
  "mall-10010691": "融合勢力定向補給",
  "mall-10010692": "心智升級特惠",
  "mall-10010693": "SVCh-猩紅夜獵手",
  "mall-10010694": "融合勢力定向補給",
  "mall-10010695": "11月特惠禮包",
  "mall-10010696": "每日特惠禮包",
  "mall-10010697": "戰術人形：賽伊·朝霧",
  "mall-10010698": "戰術人形：史黛拉·星井",
  "mall-10010699": "戰術人形：蟒蛇",
  "mall-10010700": "戰術人形：路易士",
  "mall-10010701": "戰術人形：雷電",
  "mall-10010702": "戰術人形：Mk 12",
  "mall-10010703": "蛋奶草莓芝士",
  "mall-10010704": "蛋奶草莓芝士",
  "mall-10010705": "融合勢力定向補給",
  "mall-10010706": "人力半價禮包",
  "mall-10010707": "彈藥半價禮包",
  "mall-10010708": "口糧半價禮包",
  "mall-10010709": "零件半價禮包",
  "mall-10010710": "契約半價禮包",
  "mall-10010711": "沙漠之鷹-蒼穹的迦樓羅",
  "mall-10004211": "閃光的未來",
  "mall-10004212": "戰火的刻痕",
  "mall-10004220": "先行者的贈禮",
  "mall-10004231": "獅鷲反抗軍大衣",
  "mall-10004232": "獅鷲反抗軍制服",
  "mall-10004240": "實驗型軍備",
  "mall-10004251": "反抗軍制式下裝",
  "mall-10004252": "反抗軍制式裙裝",
  "mall-10010712": "融合勢力定向補給",
  "mall-10010713": "12月特惠禮包",
  "mall-10010714": "每日特惠禮包",
  "mall-10010715": "裝扮：FNC-聖夜精靈高高掛",
  "mall-10010716": "傢具：禮物陷阱",
  "mall-10010717": "名片：粉與紫的旋渦",
  "mall-10010718": "頭像：迷失在粉眸",
  "mall-10010719": "頭像：沉醉在紫夜",
  "mall-10010721": "裝備：ImpulsIIA/C",
  "mall-10010722": "採購幣",
  "mall-10010723": "作戰報告書",
  "mall-10010724": "特種作戰報告書",
  "mall-10010725": "蛋奶草莓芝士",
  "mall-10010726": "戰術人形:M1887",
  "mall-10010727": "戰術人形:VP1915",
  "mall-10010728": "戰術人形:Cx4 風暴",
  "mall-10010729": "戰術人形:菲德洛夫",
  "mall-10010732": "蛋奶草莓芝士",
  "mall-10010733": "蛋奶草莓芝士",
  "mall-10010734": "融合勢力定向補給",
  "mall-10010735": "人力半價禮包",
  "mall-10010736": "彈藥半價禮包",
  "mall-10010737": "口糧半價禮包",
  "mall-10010738": "零件半價禮包",
  "mall-10010739": "契約半價禮包",
  "mall-10010740": "VP1915-與帕羅莎同座",
  "mall-10010741": "每日特惠禮包",
  "mall-10010742": "元旦特惠",
  "mall-10010743": "元旦限定",
  "mall-10010744": "元旦尊享",
  "mall-10099001": "裝備製造禮包",
  "mall-10099002": "裝備強化禮包",
  "mall-10099003": "心智升級禮包",
  "mall-10099004": "重裝部隊禮包",
  "mall-10099005": "收歸行動禮包",
  "mall-10099006": "融合勢力育成禮包",
  "mall-10099007": "妖精育成禮包",
  "mall-10010745": "UMP9-幽玄旅人",
  "mall-10010746": "融合勢力定向補給",
  "mall-10010747": "戰術人形：斯特林",
  "mall-10010748": "戰術人形：PPQ",
  "mall-10010749": "戰術人形：LS26",
  "mall-10010750": "戰術人形：德林加",
  "mall-10010751": "戰術人形：CZ75",
  "mall-10010752": "戰術人形：蜂鳥",
  "mall-10010753": "戰術人形：Savage 99",
  "mall-10010754": "戰術人形：TKB-408",
  "mall-10010755": "戰術人形：SP9",
  "mall-10010756": "蛋奶草莓芝士",
  "mall-10010757": "蛋奶草莓芝士",
  "mall-10010758": "戰術人形：KSG",
  "mall-10010759": "戰術人形：Saiga-12",
  "mall-10010760": "戰術人形：AA-12",
  "mall-10010761": "戰術人形：FP-6",
  "mall-10010762": "戰術人形：S.A.T.8",
  "mall-10010763": "戰術人形：MG5",
  "mall-10010764": "戰術人形：內蓋夫",
  "mall-10010765": "戰術人形：MG4",
  "mall-10010766": "戰術人形：PKP",
  "mall-10010767": "戰術人形：88式",
  "mall-10010768": "戰術人形：MG36",
  "mall-10010769": "戰術人形：G41",
  "mall-10010770": "戰術人形：HK416",
  "mall-10010771": "戰術人形：FAL",
  "mall-10010772": "戰術人形：G11",
  "mall-10010773": "戰術人形：95式",
  "mall-10010774": "戰術人形：97式",
  "mall-10010775": "戰術人形：RFB",
  "mall-10010776": "戰術人形：T91",
  "mall-10010777": "戰術人形：K2",
  "mall-10010778": "戰術人形：Zas M21",
  "mall-10010779": "戰術人形：AK-12",
  "mall-10010780": "戰術人形：AN-94",
  "mall-10010781": "戰術人形：MDR",
  "mall-10010782": "戰術人形：K11",
  "mall-10010783": "戰術人形：64式自",
  "mall-10010784": "戰術人形：ADS",
  "mall-10010785": "戰術人形：Kar98k",
  "mall-10010786": "戰術人形：WA2000",
  "mall-10010787": "戰術人形：李-恩菲爾德",
  "mall-10010788": "戰術人形：NTW-20",
  "mall-10010789": "戰術人形：M99",
  "mall-10010790": "戰術人形：IWS 2000",
  "mall-10010791": "戰術人形：卡爾卡諾M1891",
  "mall-10010792": "戰術人形：卡爾卡諾M91/38",
  "mall-10010793": "戰術人形：M200",
  "mall-10010794": "戰術人形：QBU-88",
  "mall-10010795": "戰術人形：湯姆森",
  "mall-10010796": "戰術人形：Vector",
  "mall-10010797": "戰術人形：G36C",
  "mall-10010798": "戰術人形：索米",
  "mall-10010799": "戰術人形：79式",
  "mall-10010800": "戰術人形：SR-3MP",
  "mall-10010801": "戰術人形：C-MS",
  "mall-10010802": "戰術人形：一〇〇式",
  "mall-10010803": "戰術人形：P90",
  "mall-10010804": "戰術人形：MP7",
  "mall-10010805": "戰術人形：灰熊MkⅤ",
  "mall-10010806": "戰術人形：M950A",
  "mall-10010807": "戰術人形：維爾德MkⅡ",
  "mall-10010808": "戰術人形：NZ75",
  "mall-10010809": "戰術人形：競爭者",
  "mall-10010810": "戰術人形：Px4 風暴",
  "mall-10010811": "戰術人形：PA-15",
  "mall-10010812": "戰術人形：CAWS",
  "mall-10010813": "戰術人形：DP-12",
  "mall-10010814": "戰術人形：C-93",
  "mall-10010815": "戰術人形：SIG-556",
  "mall-10010816": "戰術人形：HP-35",
  "mall-10010817": "戰術人形：AK-15",
  "mall-10010818": "戰術人形：89式自",
  "mall-10010819": "戰術人形：AK Alfa",
  "mall-10010820": "戰術人形：ZB-26",
  "mall-10010821": "戰術人形：RPK-16",
  "mall-10010822": "戰術人形：VSK-94",
  "mall-10010823": "戰術人形：S-ACR",
  "mall-10010824": "戰術人形：LTLX7000",
  "mall-10010825": "戰術人形：M6 ASW",
  "mall-10010826": "戰術人形：SVCh",
  "mall-10010827": "戰術人形：RPK-203",
  "mall-10010828": "戰術人形：SIG MCX",
  "mall-10010829": "戰術人形：德利爾",
  "mall-10010830": "戰術人形：M26-MASS",
  "mall-10010831": "戰術人形：FO-12",
  "mall-10010832": "戰術人形：A-545",
  "mall-10010833": "戰術人形：HS.50",
  "mall-10010834": "戰術人形：SR-2",
  "mall-10010835": "頭像：真核面具紀念頭像·靜風點",
  "mall-10010836": "戰術人形：斯特林",
  "mall-10010837": "戰術人形：PPQ",
  "mall-10010838": "戰術人形：LS26",
  "mall-10010839": "心智升級特惠",
  "mall-10010840": "融合勢力定向補給",
  "mall-10010841": "妖精指令補給禮包",
  "mall-10010842": "超導動能特別補給",
  "mall-10010843": "超導勢能特別補給",
  "mall-10010844": "人力半價禮包",
  "mall-10010845": "彈藥半價禮包",
  "mall-10010846": "口糧半價禮包",
  "mall-10010847": "零件半價禮包",
  "mall-10010848": "契約半價禮包",
  "mall-10010849": "每日特惠禮包",
  "mall-10010850": "重裝補給禮包",
  "mall-10010851": "甜蜜誓約禮包",
  "mall-10010852": "斯捷奇金-桃夭灼",
  "mall-10010853": "MP7-天星落",
  "mall-10010854": "TKB-408-硃砂舞",
  "mall-10010855": "融合勢力定向補給",
  "mall-10010856": "3月特惠禮包",
  "mall-10010857": "每日特惠禮包",
  "mall-10010858": "融合勢力定向補給",
  "mall-10010859": "裝扮：LWMMG-騎士與守護者",
  "mall-10010860": "名片：夜來可可香",
  "mall-10010861": "頭像：以花代語",
  "mall-10010862": "頭像：目光所向",
  "mall-10010863": "頭像：給她的巧克力",
  "mall-10010864": "裝備：P22雷射指示器 ",
  "mall-10010865": "採購幣",
  "mall-10010866": "作戰報告書",
  "mall-10010867": "特種作戰報告書",
  "mall-10010868": "蛋奶草莓芝士",
  "mall-10010869": "戰術人形:P22",
  "mall-10010870": "戰術人形:路易士",
  "mall-10010871": "戰術人形:M82",
  "mall-10010872": "戰術人形:PM1910",
  "mall-10010873": "蛋奶草莓芝士",
  "mall-10010874": "蛋奶草莓芝士",
  "mall-10010875": "K5-維納斯之陣",
  "mall-10010876": "97式-風中祝禱",
  "mall-10010877": "隼-晨露之歌",
  "mall-10010878": "融合勢力定向補給",
  "mall-10010879": "4月特惠禮包",
  "mall-10010880": "每日特惠禮包",
  "mall-10010881": "人力半價禮包",
  "mall-10010882": "彈藥半價禮包",
  "mall-10010883": "口糧半價禮包",
  "mall-10010884": "零件半價禮包",
  "mall-10010885": "契約半價禮包",
  "mall-10004511": "瀟灑的分頭",
  "mall-10004512": "成熟的長髮",
  "mall-10004520": "生活的驚喜",
  "mall-10004531": "未來的期許（男）",
  "mall-10004532": "當下的愜意（女）",
  "mall-10004540": "隨性的道具",
  "mall-10004551": "商業熱褲",
  "mall-10004552": "祈願皮履",
  "mall-10010886": "融合勢力定向補給",
  "mall-10010887": "融合勢力定向補給",
  "mall-10010888": "5月特惠禮包",
  "mall-10010889": "每日特惠禮包",
  "mall-10010890": "戰術人形:DSR-50",
  "mall-10010891": "戰術人形:M82A1",
  "mall-10010892": "戰術人形:TAC-50",
  "mall-10010893": "戰術人形:PM-9",
  "mall-10010894": "戰術人形:劉氏步槍",
  "mall-10010895": "戰術人形:Rhino",
  "mall-10010896": "蛋奶草莓芝士",
  "mall-10010897": "融合勢力定向補給",
  "mall-10010898": "心智升級特惠",
  "mall-10010899": "戰術人形：KSG",
  "mall-10010900": "戰術人形：Saiga-12",
  "mall-10010901": "戰術人形：AA-12",
  "mall-10010902": "戰術人形：FP-6",
  "mall-10010903": "戰術人形：S.A.T.8",
  "mall-10010904": "戰術人形：MG5",
  "mall-10010905": "戰術人形：內蓋夫",
  "mall-10010906": "戰術人形：MG4",
  "mall-10010907": "戰術人形：PKP",
  "mall-10010908": "戰術人形：88式",
  "mall-10010909": "戰術人形：MG36",
  "mall-10010910": "戰術人形：G41",
  "mall-10010911": "戰術人形：HK416",
  "mall-10010912": "戰術人形：FAL",
  "mall-10010913": "戰術人形：G11",
  "mall-10010914": "戰術人形：95式",
  "mall-10010915": "戰術人形：97式",
  "mall-10010916": "戰術人形：RFB",
  "mall-10010917": "戰術人形：T91",
  "mall-10010918": "戰術人形：K2",
  "mall-10010919": "戰術人形：Zas M21",
  "mall-10010920": "戰術人形：AK-12",
  "mall-10010921": "戰術人形：AN-94",
  "mall-10010922": "戰術人形：MDR",
  "mall-10010923": "戰術人形：K11",
  "mall-10010924": "戰術人形：64式自",
  "mall-10010925": "戰術人形：ADS",
  "mall-10010926": "戰術人形：Kar98k",
  "mall-10010927": "戰術人形：WA2000",
  "mall-10010928": "戰術人形：李-恩菲爾德",
  "mall-10010929": "戰術人形：NTW-20",
  "mall-10010930": "戰術人形：M99",
  "mall-10010931": "戰術人形：IWS 2000",
  "mall-10010932": "戰術人形：卡爾卡諾M1891",
  "mall-10010933": "戰術人形：卡爾卡諾M91/38",
  "mall-10010934": "戰術人形：M200",
  "mall-10010935": "戰術人形：QBU-88",
  "mall-10010936": "戰術人形：湯姆森",
  "mall-10010937": "戰術人形：Vector",
  "mall-10010938": "戰術人形：G36C",
  "mall-10010939": "戰術人形：索米",
  "mall-10010940": "戰術人形：79式",
  "mall-10010941": "戰術人形：SR-3MP",
  "mall-10010942": "戰術人形：C-MS",
  "mall-10010943": "戰術人形：一〇〇式",
  "mall-10010944": "戰術人形：P90",
  "mall-10010945": "戰術人形：MP7",
  "mall-10010946": "戰術人形：灰熊MkⅤ",
  "mall-10010947": "戰術人形：M950A",
  "mall-10010948": "戰術人形：維爾德MkⅡ",
  "mall-10010949": "戰術人形：NZ75",
  "mall-10010950": "戰術人形：競爭者",
  "mall-10010951": "戰術人形：Px4 風暴",
  "mall-10010952": "戰術人形：PA-15",
  "mall-10010953": "戰術人形：CAWS",
  "mall-10010954": "戰術人形：DP-12",
  "mall-10010955": "戰術人形：C-93",
  "mall-10010956": "戰術人形：SIG-556",
  "mall-10010957": "戰術人形：HP-35",
  "mall-10010958": "戰術人形：AK-15",
  "mall-10010959": "戰術人形：89式自",
  "mall-10010960": "戰術人形：AK-Alfa",
  "mall-10010961": "戰術人形：ZB-26",
  "mall-10010962": "戰術人形：RPK-16",
  "mall-10010963": "戰術人形：VSK-94",
  "mall-10010964": "戰術人形：S-ACR",
  "mall-10010965": "戰術人形：LTLX7000",
  "mall-10010966": "戰術人形：M6 ASW",
  "mall-10010967": "戰術人形：SVCh",
  "mall-10010968": "戰術人形：RPK-203",
  "mall-10010969": "戰術人形：SIG MCX",
  "mall-10010970": "戰術人形：德利爾",
  "mall-10010971": "戰術人形：M26-MASS",
  "mall-10010972": "戰術人形：FO-12",
  "mall-10010973": "戰術人形：A-545",
  "mall-10010974": "戰術人形：HS.50",
  "mall-10010975": "戰術人形：SR-2",
  "mall-10010976": "戰術人形：SCR",
  "mall-10010977": "頭像：真核面具紀念頭像·六周年",
  "mall-10010978": "人力半價禮包",
  "mall-10010979": "彈藥半價禮包",
  "mall-10010980": "口糧半價禮包",
  "mall-10010981": "零件半價禮包",
  "mall-10010982": "契約半價禮包",
  "mall-10010983": "重裝補給禮包",
  "mall-10010984": "Rhino-孤月之冠",
  "mall-10010985": "6月特惠禮包",
  "mall-10010986": "每日特惠禮包",
  "mall-10010987": "融合勢力定向補給",
  "mall-10010988": "妖精養成特惠",
  "mall-10010989": "VSK-94-驕陽般起舞",
  "mall-10010990": "融合勢力定向補給",
  "mall-10010991": "7月特惠禮包",
  "mall-10010992": "每日特惠禮包",
  "mall-10010993": "融合勢力定向補給",
  "mall-10010994": "人力半價禮包",
  "mall-10010995": "彈藥半價禮包",
  "mall-10010996": "口糧半價禮包",
  "mall-10010997": "零件半價禮包",
  "mall-10010998": "契約半價禮包",
  "mall-10010999": "8月特惠禮包",
  "mall-10011000": "每日特惠禮包",
  "mall-10011001": "融合勢力定向補給",
  "mall-10011002": "IWS 2000-沙堡終結者",
  "mall-10011003": "HS.50-游向蜜色海心",
  "mall-10011004": "CF05-漂浮的黑白音律",
  "mall-10011005": "裝扮：格琳娜-夏夜攝夢",
  "mall-10011006": "名片背景：爛漫夜色下的回憶",
  "mall-10011007": "頭像：萊肯旅行團初代目！",
  "mall-10011008": "頭像：熱力超標！",
  "mall-10011009": "頭像：無法融化的雪球",
  "mall-10011010": "基地背景：夜市一角",
  "mall-10011011": "裝備：奈米多功能披肩",
  "mall-10011012": "採購幣",
  "mall-10011013": "作戰報告書",
  "mall-10011014": "特種作戰報告書",
  "mall-10011015": "蛋奶草莓芝士",
  "mall-10011016": "戰術人形:Five-seveN",
  "mall-10011017": "戰術人形:ART556",
  "mall-10011018": "戰術人形:沙漠之鷹",
  "mall-10011019": "戰術人形:Savage 99",
  "mall-10011020": "戰術人形:斯特林",
  "mall-10011021": "蛋奶草莓芝士",
  "mall-10004711": "鏡面宇宙",
  "mall-10004712": "天外星系",
  "mall-10004720": "天文館紀念品",
  "mall-10004731": "觸月摘星",
  "mall-10004732": "星間航行",
  "mall-10004740": "生命保障系統",
  "mall-10004751": "游弋空間",
  "mall-10004752": "折躍光年",
  "mall-10011022": "9月特惠禮包",
  "mall-10011023": "每日特惠禮包",
  "mall-10011024": "融合勢力定向補給",
  "mall-10011025": "戰術人形：KSG",
  "mall-10011026": "戰術人形：Saiga-12",
  "mall-10011027": "戰術人形：AA-12",
  "mall-10011028": "戰術人形：FP-6",
  "mall-10011029": "戰術人形：S.A.T.8",
  "mall-10011030": "戰術人形：MG5",
  "mall-10011031": "戰術人形：內蓋夫",
  "mall-10011032": "戰術人形：MG4",
  "mall-10011033": "戰術人形：PKP",
  "mall-10011034": "戰術人形：88式",
  "mall-10011035": "戰術人形：MG36",
  "mall-10011036": "戰術人形：G41",
  "mall-10011037": "戰術人形：HK416",
  "mall-10011038": "戰術人形：FAL",
  "mall-10011039": "戰術人形：G11",
  "mall-10011040": "戰術人形：95式",
  "mall-10011041": "戰術人形：97式",
  "mall-10011042": "戰術人形：RFB",
  "mall-10011043": "戰術人形：T91",
  "mall-10011044": "戰術人形：K2",
  "mall-10011045": "戰術人形：Zas M21",
  "mall-10011046": "戰術人形：AK-12",
  "mall-10011047": "戰術人形：AN-94",
  "mall-10011048": "戰術人形：MDR",
  "mall-10011049": "戰術人形：K11",
  "mall-10011050": "戰術人形：64式自",
  "mall-10011051": "戰術人形：ADS",
  "mall-10011052": "戰術人形：Kar98k",
  "mall-10011053": "戰術人形：WA2000",
  "mall-10011054": "戰術人形：李-恩菲爾德",
  "mall-10011055": "戰術人形：NTW-20",
  "mall-10011056": "戰術人形：M99",
  "mall-10011057": "戰術人形：IWS 2000",
  "mall-10011058": "戰術人形：卡爾卡諾M1891",
  "mall-10011059": "戰術人形：卡爾卡諾M91/38",
  "mall-10011060": "戰術人形：M200",
  "mall-10011061": "戰術人形：QBU-88",
  "mall-10011062": "戰術人形：湯姆森",
  "mall-10011063": "戰術人形：Vector",
  "mall-10011064": "戰術人形：G36C",
  "mall-10011065": "戰術人形：索米",
  "mall-10011066": "戰術人形：79式",
  "mall-10011067": "戰術人形：SR-3MP",
  "mall-10011068": "戰術人形：C-MS",
  "mall-10011069": "戰術人形：一〇〇式",
  "mall-10011070": "戰術人形：P90",
  "mall-10011071": "戰術人形：MP7",
  "mall-10011072": "戰術人形：灰熊MkⅤ",
  "mall-10011073": "戰術人形：M950A",
  "mall-10011074": "戰術人形：維爾德MkⅡ",
  "mall-10011075": "戰術人形：NZ75",
  "mall-10011076": "戰術人形：競爭者",
  "mall-10011077": "戰術人形：Px4 風暴",
  "mall-10011078": "戰術人形：PA-15",
  "mall-10011079": "戰術人形：CAWS",
  "mall-10011080": "戰術人形：DP-12",
  "mall-10011081": "戰術人形：C-93",
  "mall-10011082": "戰術人形：SIG-556",
  "mall-10011083": "戰術人形：HP-35",
  "mall-10011084": "戰術人形：AK-15",
  "mall-10011085": "戰術人形：89式自",
  "mall-10011086": "戰術人形：AK-Alfa",
  "mall-10011087": "戰術人形：ZB-26",
  "mall-10011088": "戰術人形：RPK-16",
  "mall-10011089": "戰術人形：VSK-94",
  "mall-10011090": "戰術人形：S-ACR",
  "mall-10011091": "戰術人形：LTLX7000",
  "mall-10011092": "戰術人形：M6 ASW",
  "mall-10011093": "戰術人形：SVCh",
  "mall-10011094": "戰術人形：RPK-203",
  "mall-10011095": "戰術人形：SIG MCX",
  "mall-10011096": "戰術人形：德利爾",
  "mall-10011097": "戰術人形：M26-MASS",
  "mall-10011098": "戰術人形：FO-12",
  "mall-10011099": "戰術人形：A-545",
  "mall-10011100": "戰術人形：HS.50",
  "mall-10011101": "戰術人形：SR-2",
  "mall-10011102": "戰術人形：SCR",
  "mall-10011103": "戰術人形：SPAS-15",
  "mall-10011104": "戰術人形：MK3A1",
  "mall-10011105": "頭像：真核面具紀念頭像·縱向應變",
  "mall-10011106": "戰術人形：M240L",
  "mall-10011107": "戰術人形：CMR-30",
  "mall-10011108": "戰術人形：Saiga 308",
  "mall-10011109": "心智升級特惠",
  "mall-10011110": "資源特惠禮包",
  "mall-10011111": "甜蜜誓約禮包",
  "mall-10011112": "戰術人形：M240L",
  "mall-10011113": "戰術人形：CMR-30",
  "mall-10011114": "戰術人形：Saiga 308",
  "mall-10011115": "戰術人形：JS05",
  "mall-10011116": "戰術人形：ACR",
  "mall-10011117": "戰術人形：KH2002",
  "mall-10011118": "戰術人形：FARA 83",
  "mall-10011119": "戰術人形：C14",
  "mall-10011120": "戰術人形：TS12",
  "mall-10011121": "蛋奶草莓芝士",
  "mall-10011122": "蛋奶草莓芝士",
  "mall-10011123": "SR-2-本壘英豪",
  "mall-10004911": "律動飛馳",
  "mall-10004912": "奕然夢境",
  "mall-10004920": "揮汗如雨時",
  "mall-10004931": "爆裂熱魂",
  "mall-10004932": "輕舞昂揚",
  "mall-10004940": "體魄煉造器",
  "mall-10004951": "極速躍動",
  "mall-10004952": "靈動翩旋",
  "mall-10011124": "戰術人形:UMP40",
  "mall-10011125": "戰術人形:APC556",
  "mall-10011126": "戰術人形:劉氏步槍",
  "mall-10011127": "戰術人形:SL8",
  "mall-10011128": "戰術人形:AUG Para",
  "mall-10011129": "戰術人形:VHS",
  "mall-10011130": "蛋奶草莓芝士",
  "mall-10011131": "蛋奶草莓芝士",
  "mall-10011132": "10月特惠禮包",
  "mall-10011133": "每日特惠禮包",
  "mall-10011134": "人力半價禮包",
  "mall-10011135": "彈藥半價禮包",
  "mall-10011136": "口糧半價禮包",
  "mall-10011137": "零件半價禮包",
  "mall-10011138": "契約半價禮包",
  "mall-10011139": "融合勢力定向補給",
  "mall-10011140": "重裝補給禮包",
  "mall-10011141": "AUG Para-皮斯科酸",
  "mall-10011142": "SL8-幽靈菲士",
  "mall-10011143": "VHS-懸浮威士忌",
  "mall-10011144": "融合勢力定向補給",
  "mall-10011145": "融合勢力定向補給",
  "mall-10011146": "11月特惠禮包",
  "mall-10011147": "每日特惠禮包",
  "mall-10011148": "KH2002-魔獄先遣隊",
  "mall-10011149": "融合勢力定向補給",
  "mall-10011150": "12月特惠禮包",
  "mall-10011151": "每日特惠禮包",
  "mall-10011152": "QBZ-191-孤松行",
  "mall-10005011": "風中勁柳",
  "mall-10005012": "月照繁花",
  "mall-10005020": "八門心脈",
  "mall-10005031": "千紋羆虎",
  "mall-10005032": "錦緞嬌龍",
  "mall-10005040": "神兵寶器",
  "mall-10005051": "怒濤疾影",
  "mall-10005052": "飛雪無形",
  "mall-10011153": "戰術人形:SPP-1",
  "mall-10011154": "戰術人形:KSVK",
  "mall-10011155": "戰術人形:QBZ-191",
  "mall-10011156": "戰術人形:HS2000",
  "mall-10011157": "蛋奶草莓芝士",
  "mall-10011158": "蛋奶草莓芝士",
  "mall-10011159": "名片背景：宿命的天平",
  "mall-10011160": "頭像：日之榮耀",
  "mall-10011161": "頭像：月之禁海",
  "mall-10011162": "頭像：充電中……",
  "mall-10011163": "頭像：純白天使",
  "mall-10011164": "頭像：曙光的守護者",
  "mall-10011165": "基地背景：都市巡遊記",
  "mall-10011166": "裝備：M948 MODX",
  "mall-10011167": "裝備：MK318 MODX",
  "mall-10011168": "采購幣",
  "mall-10011169": "作戰報告書",
  "mall-10011170": "特種作戰報告書",
  "mall-10011171": "蛋奶草莓芝士",
  "mall-10011172": "融合勢力定向補給",
  "mall-10011173": "融合勢力定向補給",
  "mall-10011174": "每日特惠禮包",
  "mall-10011175": "元旦特惠",
  "mall-10011176": "元旦限定",
  "mall-10011177": "元旦尊享",
  "mall-10011178": "融合勢力定向補給",
  "mall-10011179": "戰術人形:CZ2000",
  "mall-10011180": "戰術人形:AUG",
  "mall-10011181": "蛋奶草莓芝士",
  "mall-10011182": "蛋奶草莓芝士",
  "mall-10011183": "帕斯卡-C12H22O11",
  "mall-10011184": "MAB高性能運動骨骼",
  "mall-10011185": "校準點券",
  "mall-10011186": "替代核心",
  "mall-10011187": "增幅膠囊",
  "mall-10011188": "采購幣",
  "mall-10011189": "特種作戰報告書",
  "mall-10011190": "蛋奶草莓芝士",
  "mall-10011191": "福兔迎春",
  "mall-10011192": "瑞兔賀歲",
  "mall-10011193": "玉兔送喜",
  "mall-10011194": "重裝補給禮包",
  "mall-10011195": "人力半價禮包",
  "mall-10011196": "彈藥半價禮包",
  "mall-10011197": "口糧半價禮包",
  "mall-10011198": "零件半價禮包",
  "mall-10011199": "契約半價禮包",
  "mall-10011200": "2月特惠禮包",
  "mall-10011201": "每日特惠禮包",
  "mall-10011202": "Px4 風暴-金風嬈",
  "mall-10011203": "塔布克-福雙至",
  "mall-10011204": "融合勢力定向補給",
  "mall-10011205": "甜蜜誓約禮包",
  "mall-10011206": "源櫻",
  "mall-10011207": "二階堂咲",
  "mall-10011208": "擴音喇叭",
  "mall-10011209": "隊長袖章",
  "mall-10011210": "愛的便當盒",
  "mall-10011211": "尾崎人偶",
  "mall-10011212": "名片：在兩千英尺處呼喚愛",
  "mall-10011213": "名片：追光燈下的合唱",
  "mall-10011214": "頭像：命運在此破局",
  "mall-10011215": "頭像：靈魂奏出絕響",
  "mall-10011216": "頭像：覺醒吧，追夢者",
  "mall-10011217": "頭像：願望吶喊出來",
  "mall-10011218": "頭像：毀滅吧！約束！",
  "mall-10011219": "頭像：汪！嗷！汪！",
  "mall-10011220": "頭像：魷！魚！絲！",
  "mall-10011221": "頭像：請永遠注視著我",
  "mall-10011222": "背景：今日晴，宜泡澡",
  "mall-10011223": "妖精：DR雞",
  "mall-10011224": "寵物：羅梅羅",
  "mall-10011225": "傢俱：古董吊燈",
  "mall-10011226": "傢俱：老友宴席",
  "mall-10011227": "佐賀好聲音",
  "mall-10011228": "舞出我傳奇",
  "mall-10011229": "水野愛",
  "mall-10011230": "紺野純子",
  "mall-10011231": "蛋奶草莓芝士",
  "mall-10011232": "3月特惠禮包",
  "mall-10011233": "每日特惠禮包",
  "mall-10011234": "SP9-浮沫白雪",
  "mall-10011235": "融合勢力定向補給"
}