[
  {
    "id": 101,
    "fight_environment_skill_id": 12020101,
    "description": "daily_event_option-10000101",
    "balance_out": 1,
    "round_duration": -1,
    "battle_duration": -1,
    "delay": 0
  },
  {
    "id": 102,
    "fight_environment_skill_id": 12020201,
    "description": "daily_event_option-10000102",
    "balance_out": 1,
    "round_duration": -1,
    "battle_duration": -1,
    "delay": 0
  },
  {
    "id": 103,
    "fight_environment_skill_id": 12020101,
    "description": "daily_event_option-10000103",
    "balance_out": 1,
    "round_duration": -1,
    "battle_duration": -1,
    "delay": 0
  },
  {
    "id": 104,
    "fight_environment_skill_id": 12020201,
    "description": "daily_event_option-10000104",
    "balance_out": 1,
    "round_duration": -1,
    "battle_duration": -1,
    "delay": 0
  },
  {
    "id": 105,
    "fight_environment_skill_id": 12020101,
    "description": "daily_event_option-10000105",
    "balance_out": 1,
    "round_duration": -1,
    "battle_duration": -1,
    "delay": 0
  },
  {
    "id": 106,
    "fight_environment_skill_id": 12020201,
    "description": "daily_event_option-10000106",
    "balance_out": 1,
    "round_duration": -1,
    "battle_duration": -1,
    "delay": 0
  },
  {
    "id": 107,
    "fight_environment_skill_id": 12020101,
    "description": "daily_event_option-10000107",
    "balance_out": 1,
    "round_duration": -1,
    "battle_duration": -1,
    "delay": 0
  },
  {
    "id": 108,
    "fight_environment_skill_id": 12020201,
    "description": "daily_event_option-10000108",
    "balance_out": 1,
    "round_duration": -1,
    "battle_duration": -1,
    "delay": 0
  },
  {
    "id": 201,
    "fight_environment_skill_id": 12020301,
    "description": "daily_event_option-10000201",
    "balance_out": 1,
    "round_duration": -1,
    "battle_duration": -1,
    "delay": 0
  },
  {
    "id": 202,
    "fight_environment_skill_id": 12020401,
    "description": "daily_event_option-10000202",
    "balance_out": 1,
    "round_duration": -1,
    "battle_duration": -1,
    "delay": 0
  },
  {
    "id": 203,
    "fight_environment_skill_id": 12020301,
    "description": "daily_event_option-10000203",
    "balance_out": 1,
    "round_duration": -1,
    "battle_duration": -1,
    "delay": 0
  },
  {
    "id": 204,
    "fight_environment_skill_id": 12020401,
    "description": "daily_event_option-10000204",
    "balance_out": 1,
    "round_duration": -1,
    "battle_duration": -1,
    "delay": 0
  },
  {
    "id": 205,
    "fight_environment_skill_id": 12020301,
    "description": "daily_event_option-10000205",
    "balance_out": 1,
    "round_duration": -1,
    "battle_duration": -1,
    "delay": 0
  },
  {
    "id": 206,
    "fight_environment_skill_id": 12020401,
    "description": "daily_event_option-10000206",
    "balance_out": 1,
    "round_duration": -1,
    "battle_duration": -1,
    "delay": 0
  },
  {
    "id": 207,
    "fight_environment_skill_id": 12020301,
    "description": "daily_event_option-10000207",
    "balance_out": 1,
    "round_duration": -1,
    "battle_duration": -1,
    "delay": 0
  },
  {
    "id": 208,
    "fight_environment_skill_id": 12020401,
    "description": "daily_event_option-10000208",
    "balance_out": 1,
    "round_duration": -1,
    "battle_duration": -1,
    "delay": 0
  },
  {
    "id": 209,
    "fight_environment_skill_id": 12020301,
    "description": "daily_event_option-10000209",
    "balance_out": 1,
    "round_duration": -1,
    "battle_duration": -1,
    "delay": 0
  },
  {
    "id": 210,
    "fight_environment_skill_id": 12020401,
    "description": "daily_event_option-10000210",
    "balance_out": 1,
    "round_duration": -1,
    "battle_duration": -1,
    "delay": 0
  },
  {
    "id": 301,
    "fight_environment_skill_id": 12020501,
    "description": "daily_event_option-10000301",
    "balance_out": 1,
    "round_duration": -1,
    "battle_duration": -1,
    "delay": 0
  },
  {
    "id": 302,
    "fight_environment_skill_id": 12020601,
    "description": "daily_event_option-10000302",
    "balance_out": 1,
    "round_duration": -1,
    "battle_duration": -1,
    "delay": 0
  },
  {
    "id": 303,
    "fight_environment_skill_id": 12020501,
    "description": "daily_event_option-10000303",
    "balance_out": 1,
    "round_duration": -1,
    "battle_duration": -1,
    "delay": 0
  },
  {
    "id": 304,
    "fight_environment_skill_id": 12020601,
    "description": "daily_event_option-10000304",
    "balance_out": 1,
    "round_duration": -1,
    "battle_duration": -1,
    "delay": 0
  },
  {
    "id": 305,
    "fight_environment_skill_id": 12020501,
    "description": "daily_event_option-10000305",
    "balance_out": 1,
    "round_duration": -1,
    "battle_duration": -1,
    "delay": 0
  },
  {
    "id": 306,
    "fight_environment_skill_id": 12020601,
    "description": "daily_event_option-10000306",
    "balance_out": 1,
    "round_duration": -1,
    "battle_duration": -1,
    "delay": 0
  },
  {
    "id": 307,
    "fight_environment_skill_id": 12020501,
    "description": "daily_event_option-10000307",
    "balance_out": 1,
    "round_duration": -1,
    "battle_duration": -1,
    "delay": 0
  },
  {
    "id": 308,
    "fight_environment_skill_id": 12020601,
    "description": "daily_event_option-10000308",
    "balance_out": 1,
    "round_duration": -1,
    "battle_duration": -1,
    "delay": 0
  },
  {
    "id": 401,
    "fight_environment_skill_id": 12021501,
    "description": "daily_event_option-10000401",
    "balance_out": 1,
    "round_duration": -1,
    "battle_duration": -1,
    "delay": 0
  },
  {
    "id": 402,
    "fight_environment_skill_id": 12021601,
    "description": "daily_event_option-10000402",
    "balance_out": 1,
    "round_duration": -1,
    "battle_duration": -1,
    "delay": 0
  },
  {
    "id": 403,
    "fight_environment_skill_id": 12021501,
    "description": "daily_event_option-10000403",
    "balance_out": 1,
    "round_duration": -1,
    "battle_duration": -1,
    "delay": 0
  },
  {
    "id": 404,
    "fight_environment_skill_id": 12021601,
    "description": "daily_event_option-10000404",
    "balance_out": 1,
    "round_duration": -1,
    "battle_duration": -1,
    "delay": 0
  },
  {
    "id": 405,
    "fight_environment_skill_id": 12021501,
    "description": "daily_event_option-10000405",
    "balance_out": 1,
    "round_duration": -1,
    "battle_duration": -1,
    "delay": 0
  },
  {
    "id": 406,
    "fight_environment_skill_id": 12021601,
    "description": "daily_event_option-10000406",
    "balance_out": 1,
    "round_duration": -1,
    "battle_duration": -1,
    "delay": 0
  },
  {
    "id": 501,
    "fight_environment_skill_id": 12020901,
    "description": "daily_event_option-10000501",
    "balance_out": 1,
    "round_duration": -1,
    "battle_duration": -1,
    "delay": 0
  },
  {
    "id": 502,
    "fight_environment_skill_id": 12021001,
    "description": "daily_event_option-10000502",
    "balance_out": 1,
    "round_duration": -1,
    "battle_duration": -1,
    "delay": 0
  },
  {
    "id": 503,
    "fight_environment_skill_id": 12020901,
    "description": "daily_event_option-10000503",
    "balance_out": 1,
    "round_duration": -1,
    "battle_duration": -1,
    "delay": 0
  },
  {
    "id": 504,
    "fight_environment_skill_id": 12021001,
    "description": "daily_event_option-10000504",
    "balance_out": 1,
    "round_duration": -1,
    "battle_duration": -1,
    "delay": 0
  },
  {
    "id": 505,
    "fight_environment_skill_id": 12020901,
    "description": "daily_event_option-10000505",
    "balance_out": 1,
    "round_duration": -1,
    "battle_duration": -1,
    "delay": 0
  },
  {
    "id": 506,
    "fight_environment_skill_id": 12021001,
    "description": "daily_event_option-10000506",
    "balance_out": 1,
    "round_duration": -1,
    "battle_duration": -1,
    "delay": 0
  },
  {
    "id": 601,
    "fight_environment_skill_id": 12022101,
    "description": "daily_event_option-10000601",
    "balance_out": 1,
    "round_duration": -1,
    "battle_duration": -1,
    "delay": 0
  },
  {
    "id": 602,
    "fight_environment_skill_id": 12022201,
    "description": "daily_event_option-10000602",
    "balance_out": 1,
    "round_duration": -1,
    "battle_duration": -1,
    "delay": 0
  },
  {
    "id": 603,
    "fight_environment_skill_id": 12022101,
    "description": "daily_event_option-10000603",
    "balance_out": 1,
    "round_duration": -1,
    "battle_duration": -1,
    "delay": 0
  },
  {
    "id": 604,
    "fight_environment_skill_id": 12022201,
    "description": "daily_event_option-10000604",
    "balance_out": 1,
    "round_duration": -1,
    "battle_duration": -1,
    "delay": 0
  },
  {
    "id": 605,
    "fight_environment_skill_id": 12022101,
    "description": "daily_event_option-10000605",
    "balance_out": 1,
    "round_duration": -1,
    "battle_duration": -1,
    "delay": 0
  },
  {
    "id": 606,
    "fight_environment_skill_id": 12022201,
    "description": "daily_event_option-10000606",
    "balance_out": 1,
    "round_duration": -1,
    "battle_duration": -1,
    "delay": 0
  },
  {
    "id": 701,
    "fight_environment_skill_id": 12021901,
    "description": "daily_event_option-10000701",
    "balance_out": 1,
    "round_duration": -1,
    "battle_duration": -1,
    "delay": 0
  },
  {
    "id": 702,
    "fight_environment_skill_id": 12022001,
    "description": "daily_event_option-10000702",
    "balance_out": 1,
    "round_duration": -1,
    "battle_duration": -1,
    "delay": 0
  },
  {
    "id": 703,
    "fight_environment_skill_id": 12021901,
    "description": "daily_event_option-10000703",
    "balance_out": 1,
    "round_duration": -1,
    "battle_duration": -1,
    "delay": 0
  },
  {
    "id": 704,
    "fight_environment_skill_id": 12022001,
    "description": "daily_event_option-10000704",
    "balance_out": 1,
    "round_duration": -1,
    "battle_duration": -1,
    "delay": 0
  },
  {
    "id": 705,
    "fight_environment_skill_id": 12021901,
    "description": "daily_event_option-10000705",
    "balance_out": 1,
    "round_duration": -1,
    "battle_duration": -1,
    "delay": 0
  },
  {
    "id": 706,
    "fight_environment_skill_id": 12022001,
    "description": "daily_event_option-10000706",
    "balance_out": 1,
    "round_duration": -1,
    "battle_duration": -1,
    "delay": 0
  },
  {
    "id": 801,
    "fight_environment_skill_id": 12022301,
    "description": "daily_event_option-10000801",
    "balance_out": 1,
    "round_duration": -1,
    "battle_duration": -1,
    "delay": 0
  },
  {
    "id": 802,
    "fight_environment_skill_id": 12022401,
    "description": "daily_event_option-10000802",
    "balance_out": 1,
    "round_duration": -1,
    "battle_duration": -1,
    "delay": 0
  },
  {
    "id": 803,
    "fight_environment_skill_id": 12022301,
    "description": "daily_event_option-10000803",
    "balance_out": 1,
    "round_duration": -1,
    "battle_duration": -1,
    "delay": 0
  },
  {
    "id": 804,
    "fight_environment_skill_id": 12022401,
    "description": "daily_event_option-10000804",
    "balance_out": 1,
    "round_duration": -1,
    "battle_duration": -1,
    "delay": 0
  },
  {
    "id": 805,
    "fight_environment_skill_id": 12022301,
    "description": "daily_event_option-10000805",
    "balance_out": 1,
    "round_duration": -1,
    "battle_duration": -1,
    "delay": 0
  },
  {
    "id": 806,
    "fight_environment_skill_id": 12022401,
    "description": "daily_event_option-10000806",
    "balance_out": 1,
    "round_duration": -1,
    "battle_duration": -1,
    "delay": 0
  },
  {
    "id": 901,
    "fight_environment_skill_id": 12020701,
    "description": "daily_event_option-10000901",
    "balance_out": 1,
    "round_duration": -1,
    "battle_duration": -1,
    "delay": 0
  },
  {
    "id": 902,
    "fight_environment_skill_id": 12020801,
    "description": "daily_event_option-10000902",
    "balance_out": 1,
    "round_duration": -1,
    "battle_duration": -1,
    "delay": 0
  },
  {
    "id": 903,
    "fight_environment_skill_id": 12020701,
    "description": "daily_event_option-10000903",
    "balance_out": 1,
    "round_duration": -1,
    "battle_duration": -1,
    "delay": 0
  },
  {
    "id": 904,
    "fight_environment_skill_id": 12020801,
    "description": "daily_event_option-10000904",
    "balance_out": 1,
    "round_duration": -1,
    "battle_duration": -1,
    "delay": 0
  },
  {
    "id": 905,
    "fight_environment_skill_id": 12020701,
    "description": "daily_event_option-10000905",
    "balance_out": 1,
    "round_duration": -1,
    "battle_duration": -1,
    "delay": 0
  },
  {
    "id": 906,
    "fight_environment_skill_id": 12020801,
    "description": "daily_event_option-10000906",
    "balance_out": 1,
    "round_duration": -1,
    "battle_duration": -1,
    "delay": 0
  },
  {
    "id": 1001,
    "fight_environment_skill_id": 12021101,
    "description": "daily_event_option-10001001",
    "balance_out": 1,
    "round_duration": -1,
    "battle_duration": -1,
    "delay": 0
  },
  {
    "id": 1002,
    "fight_environment_skill_id": 12021201,
    "description": "daily_event_option-10001002",
    "balance_out": 1,
    "round_duration": -1,
    "battle_duration": -1,
    "delay": 0
  },
  {
    "id": 1003,
    "fight_environment_skill_id": 12021101,
    "description": "daily_event_option-10001003",
    "balance_out": 1,
    "round_duration": -1,
    "battle_duration": -1,
    "delay": 0
  },
  {
    "id": 1004,
    "fight_environment_skill_id": 12021201,
    "description": "daily_event_option-10001004",
    "balance_out": 1,
    "round_duration": -1,
    "battle_duration": -1,
    "delay": 0
  },
  {
    "id": 1005,
    "fight_environment_skill_id": 12021101,
    "description": "daily_event_option-10001005",
    "balance_out": 1,
    "round_duration": -1,
    "battle_duration": -1,
    "delay": 0
  },
  {
    "id": 1006,
    "fight_environment_skill_id": 12021201,
    "description": "daily_event_option-10001006",
    "balance_out": 1,
    "round_duration": -1,
    "battle_duration": -1,
    "delay": 0
  },
  {
    "id": 1101,
    "fight_environment_skill_id": 12021701,
    "description": "daily_event_option-10001101",
    "balance_out": 1,
    "round_duration": -1,
    "battle_duration": -1,
    "delay": 0
  },
  {
    "id": 1102,
    "fight_environment_skill_id": 12021801,
    "description": "daily_event_option-10001102",
    "balance_out": 1,
    "round_duration": -1,
    "battle_duration": -1,
    "delay": 0
  },
  {
    "id": 1103,
    "fight_environment_skill_id": 12021701,
    "description": "daily_event_option-10001103",
    "balance_out": 1,
    "round_duration": -1,
    "battle_duration": -1,
    "delay": 0
  },
  {
    "id": 1104,
    "fight_environment_skill_id": 12021801,
    "description": "daily_event_option-10001104",
    "balance_out": 1,
    "round_duration": -1,
    "battle_duration": -1,
    "delay": 0
  },
  {
    "id": 1105,
    "fight_environment_skill_id": 12021701,
    "description": "daily_event_option-10001105",
    "balance_out": 1,
    "round_duration": -1,
    "battle_duration": -1,
    "delay": 0
  },
  {
    "id": 1106,
    "fight_environment_skill_id": 12021801,
    "description": "daily_event_option-10001106",
    "balance_out": 1,
    "round_duration": -1,
    "battle_duration": -1,
    "delay": 0
  },
  {
    "id": 1201,
    "fight_environment_skill_id": 12021301,
    "description": "daily_event_option-10001201",
    "balance_out": 1,
    "round_duration": -1,
    "battle_duration": -1,
    "delay": 0
  },
  {
    "id": 1202,
    "fight_environment_skill_id": 12021401,
    "description": "daily_event_option-10001202",
    "balance_out": 1,
    "round_duration": -1,
    "battle_duration": -1,
    "delay": 0
  },
  {
    "id": 1203,
    "fight_environment_skill_id": 12021301,
    "description": "daily_event_option-10001203",
    "balance_out": 1,
    "round_duration": -1,
    "battle_duration": -1,
    "delay": 0
  },
  {
    "id": 1204,
    "fight_environment_skill_id": 12021401,
    "description": "daily_event_option-10001204",
    "balance_out": 1,
    "round_duration": -1,
    "battle_duration": -1,
    "delay": 0
  },
  {
    "id": 1205,
    "fight_environment_skill_id": 12021301,
    "description": "daily_event_option-10001205",
    "balance_out": 1,
    "round_duration": -1,
    "battle_duration": -1,
    "delay": 0
  },
  {
    "id": 1206,
    "fight_environment_skill_id": 12021401,
    "description": "daily_event_option-10001206",
    "balance_out": 1,
    "round_duration": -1,
    "battle_duration": -1,
    "delay": 0
  },
  {
    "id": 1301,
    "fight_environment_skill_id": 12022501,
    "description": "daily_event_option-10001301",
    "balance_out": 1,
    "round_duration": -1,
    "battle_duration": -1,
    "delay": 0
  },
  {
    "id": 1302,
    "fight_environment_skill_id": 12022501,
    "description": "daily_event_option-10001302",
    "balance_out": 1,
    "round_duration": -1,
    "battle_duration": -1,
    "delay": 0
  },
  {
    "id": 1401,
    "fight_environment_skill_id": 12022601,
    "description": "daily_event_option-10001401",
    "balance_out": 1,
    "round_duration": -1,
    "battle_duration": -1,
    "delay": 0
  },
  {
    "id": 1402,
    "fight_environment_skill_id": 12022601,
    "description": "daily_event_option-10001402",
    "balance_out": 1,
    "round_duration": -1,
    "battle_duration": -1,
    "delay": 0
  },
  {
    "id": 1501,
    "fight_environment_skill_id": 12022701,
    "description": "daily_event_option-10001501",
    "balance_out": 1,
    "round_duration": -1,
    "battle_duration": -1,
    "delay": 0
  },
  {
    "id": 1502,
    "fight_environment_skill_id": 12022701,
    "description": "daily_event_option-10001502",
    "balance_out": 1,
    "round_duration": -1,
    "battle_duration": -1,
    "delay": 0
  },
  {
    "id": 1601,
    "fight_environment_skill_id": 12022801,
    "description": "daily_event_option-10001601",
    "balance_out": 1,
    "round_duration": -1,
    "battle_duration": -1,
    "delay": 0
  },
  {
    "id": 1701,
    "fight_environment_skill_id": 12022901,
    "description": "daily_event_option-10001701",
    "balance_out": 1,
    "round_duration": -1,
    "battle_duration": -1,
    "delay": 0
  },
  {
    "id": 1702,
    "fight_environment_skill_id": 12022901,
    "description": "daily_event_option-10001702",
    "balance_out": 1,
    "round_duration": -1,
    "battle_duration": -1,
    "delay": 0
  },
  {
    "id": 1801,
    "fight_environment_skill_id": 12023001,
    "description": "daily_event_option-10001801",
    "balance_out": 1,
    "round_duration": -1,
    "battle_duration": -1,
    "delay": 0
  },
  {
    "id": 1901,
    "fight_environment_skill_id": 12023301,
    "description": "daily_event_option-10001901",
    "balance_out": 1,
    "round_duration": -1,
    "battle_duration": -1,
    "delay": 0
  },
  {
    "id": 2001,
    "fight_environment_skill_id": 12023201,
    "description": "daily_event_option-10002001",
    "balance_out": 1,
    "round_duration": -1,
    "battle_duration": -1,
    "delay": 0
  },
  {
    "id": 2002,
    "fight_environment_skill_id": 12023201,
    "description": "daily_event_option-10002002",
    "balance_out": 1,
    "round_duration": -1,
    "battle_duration": -1,
    "delay": 0
  }
]